{
	"S30-1797": "qwTlfI5fzfP",
	"O60-1350": "oWfk8oX2GbX",
	"O60-1373": "xnjcjXB7CEn",
	"H15-566": "T2PLJ5p9q3h",
	"H49-593": "u5fPmcaPHzE",
	"R20-1680": "SRfzWO6DW0y",
	"R20-1678": "FIiUyLpb7BD",
	"C51-280": "X3w5ZEbaS0A",
	"W50-1912": "IeEancdOEUa",
	"Z30-2002": "eRgIVzMbDoJ",
	"Q90-1608": "n0MzXkCf5bk",
	"G50-517": "db2KowpHFmK",
	"K00-806": "sBmxZyxm5q2",
	"Q30-1558": "jqvPT8L39Ez",
	"E10-352": "DlTD6TX62RL",
	"R50-1740": "yujrAjfEpAb",
	"A00-11": "GrqAoWI6dqO",
	"P35-1489": "K6hMvf5iXCG",
	"T79-1890": "jFkEEkCE4gl",
	"G90-548": "mvDv4dlN3KQ",
	"Z20-1965": "tf44WsBLDMq",
	"K00-772": "yWGyrqbzvM0",
	"N40-1118": "HbDdNVs2ECL",
	"A80-120": "xKGkDReeQKF",
	"T66-1887": "mKjXtgaFQfa",
	"R00-1610": "rjJIC8ltYNN",
	"S30-1802": "v7SqmBtFaHh",
	"J09-717": "kPgwhF12UFV",
	"R20-1668": "ssn5T67sCjc",
	"I20-635": "CklHt59PZsZ",
	"N80-1186": "TdFoV7MmyyN",
	"A90-131": "KW6voUkIESr",
	"Z40-2019": "lJ2z4SmyC7q",
	"F30-467": "yGu9Rd8G4BE",
	"T08-1849": "wiAgmX1N0Fu",
	"F80-487": "LzJHcNh1Wy2",
	"F40-481": "is3hjdxtKGa",
	"D65-327": "DgrE0rXzA9r",
	"P70-1523": "uPfhFbtvrT5",
	"X85-1914": "KdGskA8Fq6A",
	"R10-1653": "poliMsehcEZ",
	"P90-1540": "H8pJnfjHoCn",
	"O20-1233": "XBglnqPMGiy",
	"O60-1322": "S4GMc9Dl0SV",
	"P20-1484": "uA02jNs1vKu",
	"Y85-1928": "N766jy1gl94",
	"E00-350": "TdF3nC6fM2Q",
	"C15-262": "SbceAf6rgWH",
	"M00-1006": "G07Mk7OoHT1",
	"I80-700": "fhWIAmItKF9",
	"Y83-1919": "vPauxKqlQFH",
	"O60-1337": "bBxLanL0ohB",
	"I30-670": "u3kY5GZxEhm",
	"L60-986": "O4q0iXb7quZ",
	"E10-394": "bOs1cEM24Sy",
	"R00-1633": "zBPaUwFFG4D",
	"Z40-2039": "RcSBuPCwrdM",
	"Z30-1977": "MVL2NBWtt0C",
	"N80-1163": "am8QQGXBPEF",
	"I05-617": "HUbHOkTQqNH",
	"F50-482": "Acy48OnLU6n",
	"O00-1191": "Adz27IiCKga",
	"Z30-1983": "Q2dnF1NLaXx",
	"B95-254": "ztAEy63DBIc",
	"H30-574": "JPA4Bax1POO",
	"L20-940": "Ql4hO0HVVSn",
	"N40-1117": "jPFhiO3yyjS",
	"O00-1208": "PItxOKAKsB0",
	"B65-214": "CC2q9UggBEm",
	"P50-1521": "nuXUCC96Rl7",
	"B20-166": "m3l3j5lDoF1",
	"E10-391": "M1IwP09wnYA",
	"B90-249": "japGIUqsIrE",
	"G80-531": "HGYcvKK5RXV",
	"O20-1239": "NwEqyerhm0D",
	"I20-629": "jiPK4ddC4Ot",
	"F90-491": "RaD6Oki3qZH",
	"R20-1674": "nUZAzKIZsWu",
	"T66-1877": "O27MrWA1eZ1",
	"M05-1014": "bdJojOOa3wB",
	"C76-289": "PIlm1VY4H6I",
	"R10-1641": "sLb76Jbml1R",
	"O60-1321": "x8kzLvsN2gE",
	"O30-1279": "lH6LbkboZsO",
	"R10-1652": "R34gbZYVX6F",
	"I00-610": "Fyy7LLGbasw",
	"E50-425": "eepaFJUuCA6",
	"K00-756": "SCIH6xnCoEx",
	"K35-834": "JpKwnYky9Xq",
	"A30-68": "zWj8HHFhqka",
	"Z30-1981": "DRe6Alvkf6x",
	"A20-59": "DVKb5IcNMh2",
	"Z40-2032": "KWbLP1ZLESx",
	"B65-220": "nzFQaupOXNB",
	"K00-811": "CXyV3GBIKCr",
	"K80-899": "jBXMEFKlQVU",
	"P90-1535": "AY2dN11R2rv",
	"R10-1655": "CT9lp17Jon9",
	"K40-844": "ZdE8di7R1XV",
	"Z00-1937": "NVPbpwvsfxn",
	"N25-1095": "Rh6KhKkdy9C",
	"P35-1500": "x4h2edsni8p",
	"O60-1328": "l6bi2xelmnv",
	"O30-1276": "OrUAa3eJ9Yi",
	"W00-1907": "m3GtEYwKbnV",
	"G80-532": "Ll7TQNykHWB",
	"R10-1661": "LbjjTArmvcT",
	"J09-724": "S7LzYwzzc6u",
	"T80-1904": "Ph6wVPQVlKK",
	"Q65-1593": "kK4kCcZ9FfY",
	"K55-870": "SWMX42n9d9Q",
	"G00-492": "c75pCUpcgBc",
	"P50-1517": "texCnKnNAy6",
	"Q35-1563": "rJoUvlCgHJu",
	"R50-1757": "g8vm2Xt4UEy",
	"R47-1735": "qZXjGiTaPnP",
	"Z00-1955": "YK00yQM4aCP",
	"H49-592": "Oe2P2dXHCrd",
	"D80-334": "m8L1q5s7ov3",
	"K00-797": "CgyeKsOfEnB",
	"P10-1463": "j5Vw050udzW",
	"R00-1613": "cvDDZsGu0yW",
	"D70-333": "yYgYJAiXj2i",
	"H15-569": "jVs5R1VvM43",
	"H40-577": "Wx2RNQXx4mO",
	"H43-584": "dLqXhlBUKH8",
	"K00-794": "ilCiEwJ1bbT",
	"Y83-1921": "TCpujYOl9tu",
	"A15-54": "VwCR42TvuPu",
	"A00-25": "O9qUibCr9wT",
	"Q65-1590": "Qbic76b2RNB",
	"S50-1811": "jLa8nygj5bR",
	"R50-1761": "z0m68dOZ0Ue",
	"A00-26": "NOixPCs041N",
	"E40-409": "kog9cdOzsJC",
	"M91-1075": "EAYJL4tSJ1U",
	"I30-657": "NtLHtEAmQsh",
	"Q38-1572": "tsBxtCBlZXm",
	"O10-1221": "FdUPewfWpsg",
	"S00-1778": "qB4QZUwFDQQ",
	"J95-740": "SoQmouADjUT",
	"I60-692": "dxMJ4UmMaTQ",
	"O60-1341": "Fjm71TbfMAX",
	"Z40-2016": "ErNDlLcKIdE",
	"C76-290": "fdhTfXUr7bz",
	"E70-436": "T5MvrDTXCXG",
	"E20-405": "zdQOpYlcibb",
	"L40-963": "demxoX41SZQ",
	"L80-996": "m5wq5s8Wk5L",
	"O10-1230": "WERL7LjT4x5",
	"A00-33": "M6uX9x8qKTz",
	"K00-778": "nA2i0ZseCkh",
	"B50-209": "mBIOszcLiDw",
	"K90-908": "uzhvojoVViH",
	"I60-684": "FCV0jbteVWx",
	"Z00-1957": "BvmvDvvZckf",
	"I20-636": "nmTEj82fxiJ",
	"L40-955": "j1ZTTYOYBIU",
	"B65-226": "XSJUYtZAHZ1",
	"L60-991": "ivUTnhPjBY5",
	"L80-1001": "K1GUOQe3y3o",
	"Q38-1570": "twgrzFD3o23",
	"S00-1777": "jiehxPY116H",
	"D70-332": "qgWgrLLxb1N",
	"O60-1344": "LnKsjab9Le4",
	"L80-998": "hHlbSDn3Azp",
	"O60-1316": "YPlLcF0P6Iq",
	"Z20-1962": "EMkFUFfmVA0",
	"E10-382": "Wi0nwprPSpU",
	"Q00-1544": "C4uZbzcrQfw",
	"K00-742": "lXtQAcMfoYf",
	"O85-1395": "JtE7zrxypXo",
	"A30-78": "lAjheviHrzl",
	"E10-379": "CUy6XB3O9vY",
	"O20-1238": "vemQjSjK6hY",
	"P05-1449": "S5ZMbZwwAj5",
	"A15-46": "SPBQtv3x4Ab",
	"O30-1273": "G1Jh6qEesmr",
	"E10-374": "jwLkHrXqFwT",
	"A50-85": "vIpVfa60UUz",
	"D60-326": "kEx8eb5qDM6",
	"M20-1030": "eVQw8MD7lUF",
	"P10-1455": "HjOfrhElEKp",
	"M86-1070": "seNVHiiz48q",
	"E10-366": "FdSfqcyiZPb",
	"N80-1146": "ajVgdhDkzVF",
	"O80-1388": "ApcqPG3aI1W",
	"Z00-1933": "Y2uw3bUnGaD",
	"K40-845": "Cfgu90ER8cZ",
	"I20-626": "PJGhVL8BJMY",
	"M05-1008": "LZeuRl5Xoe3",
	"G90-544": "elZ6BwVgrpA",
	"K55-873": "cmZDOp42uaF",
	"B35-191": "dWoVSnDf7PC",
	"B00-149": "lEfEwA843gm",
	"K00-749": "PCiCaNaV9Ep",
	"A15-57": "Ssbc1rGlKu1",
	"K55-869": "otKxUqySlzv",
	"N80-1181": "mkO3ng579PS",
	"B35-181": "YZnOj1nq1cN",
	"C60-285": "kwWc7BmMV7L",
	"O20-1257": "ztj8i66W4H3",
	"K55-877": "pWX4EFFwilu",
	"M80-1066": "YtjdN4tFeyy",
	"B65-234": "rtJ2YvwF1sc",
	"T66-1874": "JDByrUulkx9",
	"A30-61": "rERUD6UlVx6",
	"E10-378": "EBAlcfjZV04",
	"I30-644": "I5VRqnCcPQO",
	"A65-105": "jKALRdwoqC4",
	"J00-710": "dZ2QPsdrpJZ",
	"P20-1483": "KoiPZqM96oq",
	"G40-509": "m4JHVzX3toX",
	"K00-795": "O37XEqIom0F",
	"F30-462": "S55SnJUjkZq",
	"H65-609": "UzEIx6asf4s",
	"B15-152": "V69rOKsOur4",
	"O00-1188": "EqHBWSa9yxf",
	"G40-494": "IjGLVoN8gVD",
	"I60-689": "xYuuKYZSg6w",
	"P50-1502": "pCdKK2bVugg",
	"N80-1171": "Rtd6V68sbw7",
	"Z30-1982": "QG7E1M1uBpO",
	"N30-1108": "YAwXIKSuf7r",
	"K00-765": "WKbBz3Lp63h",
	"L20-929": "fzMLyQ0emJc",
	"P05-1450": "ZH4kYX6rqK4",
	"D10-319": "i8XwnzAVhNd",
	"R50-1770": "ftHU7325iis",
	"I80-697": "edBcScvUnXn",
	"O20-1270": "czh9apDQY0t",
	"T80-1891": "GWk4jXRk23e",
	"H10-557": "RhFWHiYPFHA",
	"J90-738": "EfyDP5lkAGB",
	"S30-1798": "Q5hePf3O938",
	"C76-288": "XWZFFarPqWS",
	"Z40-2040": "CUZWq94gP3n",
	"S40-1808": "VXBcJlhZ0Xp",
	"H40-579": "STraqzzgKHn",
	"T15-1853": "t6Y12DWwn44",
	"N80-1167": "n1CW632fAqb",
	"R40-1715": "GlpEFLCZJkF",
	"O30-1282": "jX8QnjGYIFU",
	"O00-1216": "HFXKYD9d9In",
	"M05-1021": "GTWB3zpJfFN",
	"K70-887": "W1M1ZCmKLLp",
	"E10-357": "wRRlHfhSVIo",
	"K70-889": "mqXjhhirM6L",
	"P05-1438": "SYP6R9bLBIf",
	"P05-1447": "rm7AEz7cj4A",
	"N40-1122": "WADWu3tVuHp",
	"K20-828": "a9HHAP7tUsW",
	"K55-872": "MUxQ7Ha5Lie",
	"Z00-1945": "R8fgMDfXpz7",
	"P90-1539": "gGAu8MP0xFp",
	"K35-831": "wmhbs77VBSz",
	"K40-849": "gKt7evyt8tw",
	"D65-328": "YTy7pC0OsSo",
	"N20-1093": "QR7BkgB7Wwe",
	"O94-1403": "YWWHSHXkj6f",
	"K00-762": "arA2h8fW4My",
	"J09-722": "ygYEyjJeWGU",
	"I30-651": "JdR62JUSgvb",
	"L50-969": "wA7pkL5WiI1",
	"N20-1089": "fJMOdu1mfW4",
	"E00-349": "cwoGUSBEFZp",
	"N80-1184": "iyTOogN0UeM",
	"Q80-1598": "uFUnucisakT",
	"B65-232": "TwSsdM17b3W",
	"R50-1773": "XjdxmVOCqJC",
	"N80-1177": "UM3LH1z0CfO",
	"Z00-1946": "ljI2EMqv3cV",
	"S20-1795": "dsMbB1JN7HE",
	"K55-864": "tkaxqPIj0Z2",
	"B50-211": "vKY9BGNN3in",
	"K50-855": "Z4BVihEPQJV",
	"R00-1614": "vnoz4mX71je",
	"G80-530": "aksNOqr78y9",
	"O60-1324": "YUO4RO0K7hW",
	"P20-1468": "QlXGvUWG56g",
	"J00-711": "A6Kxt5h3fcC",
	"B35-187": "k27KeQpJRYm",
	"R47-1736": "ngUDrXxW8Ml",
	"H15-565": "PAQbz9nBl6h",
	"N80-1158": "iETAWib1rbQ",
	"E40-410": "ZAQb6v1GfTF",
	"I70-694": "dNUcPFJeZfK",
	"G80-525": "tlN5gxNKskb",
	"G90-541": "zOHGvqycgXN",
	"Z40-2025": "tQVhKKnz2Xi",
	"Z40-2021": "eg3floJ9ZOV",
	"R10-1648": "ChFCwnPGu4x",
	"O60-1333": "EybTH4giFxH",
	"L40-958": "PLcg2tPLwY6",
	"G50-516": "mmWv5l5Bnf5",
	"N60-1124": "PbLxoKJPcuK",
	"A50-94": "VvQtDYaw8cL",
	"F20-461": "MTBgnP30fiP",
	"O60-1338": "KV4C98LT9iZ",
	"B85-236": "dapSmrQnglG",
	"T51-1870": "nRwcfnFMDoE",
	"O60-1370": "GHQ1vAgTXqE",
	"E40-407": "nKn1Lyugu25",
	"S00-1790": "qaGaIO6pFwv",
	"K40-854": "OgdYPe7dHBC",
	"B35-192": "KyxupIxueOe",
	"A00-20": "kAnB4ZfICf3",
	"M05-1028": "Cyj5RaFQ0jq",
	"M65-1059": "MN174C1gBON",
	"O00-1196": "Vul7eRyY5QI",
	"B35-171": "ewGKHi5dKLk",
	"P05-1439": "HQLJ2XjveLI",
	"K00-775": "ZHm4rbXSVH8",
	"K20-824": "bB945Bq6rep",
	"N80-1140": "zDLxYPAuznf",
	"O60-1348": "Z37i0wwAvjH",
	"M80-1069": "xSUWfYU4siA",
	"N80-1169": "zrKfMF0UA6d",
	"M91-1074": "kBKaOAFgvTJ",
	"N10-1083": "Tdugye9vJgS",
	"O94-1406": "Od7Du4C99OB",
	"E40-408": "v1BCpGFT8Xs",
	"Q60-1582": "DGjdOG4BnqM",
	"Z00-1950": "KMXW99LxhxC",
	"N70-1130": "Uk8CUcY8bmv",
	"K40-852": "HSc2drLgdNP",
	"Y90-1930": "p6b3T6cZggd",
	"R40-1723": "UTXKp0jGFMd",
	"H40-580": "KfE9z1x5BgT",
	"Z30-1999": "lz1lT9MFQd4",
	"O10-1220": "qpZtM8FCOK2",
	"Z00-1952": "EZBHVuim8t7",
	"B50-202": "xb597ZmVbCq",
	"Z40-2013": "oFyNd3ixy1Z",
	"P10-1452": "MQyCxAwY15h",
	"I80-706": "kYNV5jlcSmt",
	"E10-355": "iarRpdTn0BE",
	"I30-674": "i6RHoeMY4qg",
	"T20-1857": "hnlUlFrmrTA",
	"R00-1612": "Lsjxm1PS5F2",
	"I80-699": "UZZFTzoS259",
	"K00-779": "R7xL2xJ5o2D",
	"F40-478": "Lu1N9iErAZ1",
	"B50-198": "ITGJpcL9wra",
	"S70-1822": "BsMmnIOvZgn",
	"Z30-1988": "lGme383bPPi",
	"G40-511": "K0FF2a6WYE9",
	"O00-1206": "eH5R9j4LrIG",
	"N80-1165": "fiWI8zKYi2S",
	"B20-162": "yWn5lfYoONe",
	"D10-314": "gzDkWH6SYH6",
	"B50-200": "SnKf3dD3W5T",
	"O00-1198": "aXMzQlifElC",
	"N70-1129": "VzlLiCXMp14",
	"O80-1390": "jr2KpJZ1Z7A",
	"R00-1634": "kVaSegwkoGD",
	"O00-1203": "HFck4pPOpOw",
	"B20-167": "RwwvlXu5lo6",
	"I95-708": "QBK9VIIvuhP",
	"C81-310": "zNjAPsnHmm6",
	"M70-1063": "Kjia3Vuy6W9",
	"F30-468": "UNjfzRccgDQ",
	"R00-1637": "HMwcXJYfGPx",
	"I05-615": "X06mUo9DWF4",
	"K55-860": "FD3OSpRgi1C",
	"L80-1003": "trTvmxWrkIO",
	"S50-1816": "kEedhPC5eXo",
	"P90-1541": "iOMUvBju61m",
	"S10-1792": "Bog4SAZtOpY",
	"K00-780": "fW1DBaYk1Uz",
	"A30-76": "Hp22cvTx3Gx",
	"G40-510": "GHHh89pbLoR",
	"I95-709": "nORDN2wkORJ",
	"A80-122": "HNgPAivnI2U",
	"O10-1229": "KpTe9J3dNso",
	"T80-1901": "d7f1CXmEwP7",
	"T66-1878": "a5gA2HeGglW",
	"O30-1285": "ZvxlgI1dwyH",
	"P00-1416": "mNMAqsupPxB",
	"M20-1037": "LfkIAhty7hJ",
	"L60-982": "tm3Ru2jZwvZ",
	"A30-72": "oibOkVun9zM",
	"S80-1824": "diRGai67ta5",
	"A90-126": "pej2aR5T4d3",
	"P10-1456": "AncuzIGiTfu",
	"K40-843": "FXqXt4DAfjH",
	"Q65-1596": "Camo5Ivbybh",
	"G50-514": "aQoezdIuuM1",
	"B95-250": "MX58l4IqjOg",
	"O20-1259": "wJLZfkyOx5c",
	"R20-1671": "aOVJuWFOGA6",
	"O20-1252": "sNzdVoBXJ5D",
	"K40-842": "nSoKf2Qn2Qc",
	"N60-1127": "MWcgHfNo7y4",
	"R00-1618": "iOhlTjGYxpt",
	"B35-179": "ImmXlmeoHEi",
	"C30-271": "SvMkLh2jZuh",
	"Z30-1997": "f3aWK6vrsZZ",
	"Q20-1556": "I8G9q66MTq1",
	"S00-1789": "SNPvTC26ipS",
	"B50-210": "fQik4epyCTz",
	"Z00-1948": "STsAAjMhowP",
	"F30-463": "OrgiiQNipUp",
	"Z40-2030": "gdmMKvLRu2E",
	"M50-1050": "gqJrLA3nv7b",
	"L10-923": "cLVK64o0dOm",
	"S00-1787": "zpRZ1fogUsF",
	"M30-1041": "aj5S0TAC28T",
	"A00-17": "xtfA4IgPS0I",
	"C76-293": "pQOUWulCc5Z",
	"K90-907": "whY59LFxevH",
	"O20-1240": "wGcEzX7USI5",
	"P00-1434": "BkU3LuLPj05",
	"L00-912": "IpkWptw2BBT",
	"E10-371": "dUQrAoaGDsB",
	"P90-1532": "tRROt5MFDlS",
	"K00-757": "DPkTtJHXDbD",
	"M60-1056": "bqzAb7ryiOS",
	"C15-264": "gBDsfH87u84",
	"O60-1349": "Yrg9lkVjxHI",
	"U00-2054": "zdadZ5UOJWc",
	"K00-766": "OFT7QLL1tXL",
	"T66-1876": "qPLSEtQQ9NK",
	"R50-1752": "WyXCtGmztq1",
	"J09-723": "O1JEk23YORx",
	"H65-607": "QIxTjkoTKZT",
	"P35-1496": "Pbvr2NCRKoq",
	"I30-672": "OV00wO8SnXg",
	"L80-1005": "Vvhq6epfXNm",
	"F60-484": "JdIGXwLifZ9",
	"R10-1656": "m5cqi9UlRJo",
	"A15-38": "M8XWDuvqWqh",
	"B00-135": "y2HBYMD8Njd",
	"O80-1385": "rU9Hn8vUDwc",
	"A30-63": "Fl5II91OSil",
	"G40-497": "rTv1lT57h1S",
	"T29-1863": "lxILE7LHkSw",
	"K70-885": "fHfF6Tj8LOc",
	"N20-1090": "ki4hnLLc917",
	"O80-1387": "CQeXHWazWBa",
	"B65-219": "ivwrPlf8ESm",
	"C81-312": "B4FrNvJ0v1r",
	"K00-812": "aAL2lp9NgeT",
	"Q38-1568": "Yk6BeJdrVAo",
	"O60-1320": "HhGUfv1Yfqk",
	"P50-1513": "rq0nd3LGFnu",
	"Q65-1592": "VJhGzSaoNnG",
	"C76-295": "LAFyr70BTfU",
	"M05-1017": "B3tW7ZYNs8q",
	"P00-1415": "T1i9bqGgelr",
	"K35-832": "ePABKqd3b8M",
	"R50-1750": "wv0Y6W4Am6r",
	"O80-1379": "NVLiesWcCxf",
	"K20-821": "OQuVPfLEpFZ",
	"W00-1906": "p9GItSkd2My",
	"B85-241": "lg5JfPGTVw5",
	"L50-970": "NgP2qREJ938",
	"R00-1631": "vUntNUFoaiJ",
	"I20-631": "qFLMBGN4Q6i",
	"L60-992": "El3WsBOXvnu",
	"R50-1771": "axOsQB8zfaS",
	"I60-691": "Xx80qeKBqsm",
	"M50-1052": "ZoUJ68B0Iyz",
	"R25-1685": "oEs4APY8kd1",
	"A00-6": "cvB8yFu3Er0",
	"A30-70": "fPJEkD45HRY",
	"Q35-1562": "XeU39QsJd4G",
	"Q20-1557": "zsssoyijAKM",
	"F20-453": "JzYvETgzIS9",
	"O10-1217": "YBlOR5P2wXY",
	"G90-538": "STHUyNYPMLy",
	"T08-1848": "l0xyrspwwCc",
	"I10-623": "OcpPlZ951c3",
	"B35-186": "KVmUlrxGLOy",
	"A00-4": "Iuos0MOfsb9",
	"Z40-2036": "TMPXr1aC8w4",
	"K40-836": "ULnfZzThlno",
	"E00-346": "ro8CeBARw6B",
	"Q50-1578": "gBiVCwJDlSq",
	"G40-507": "KczUPCSMUlt",
	"G90-539": "GPxe3643KaJ",
	"E10-369": "kq6k57GWSIl",
	"F30-464": "ml2P1ZTk6CT",
	"D60-323": "ZQNWh3Kfb3S",
	"Z30-2007": "ubd4HcRzLYK",
	"K20-820": "fCOEaMkj1gE",
	"O30-1289": "uYTTNfHAZ18",
	"E00-351": "rgJWMPBirFU",
	"N00-1078": "b8HzKNQaWbJ",
	"M86-1073": "EYttWXDDGID",
	"S80-1829": "EPRTiiI0eUA",
	"R10-1646": "LeM6VQSMlxQ",
	"O20-1268": "erxlcxBNgEl",
	"A50-87": "g82dirtQBiN",
	"J20-725": "Kk1mikdvguH",
	"I30-669": "peVSurGAbPk",
	"A00-10": "zYPcbGo7dIB",
	"O30-1294": "YLvinXoPLdQ",
	"F20-460": "w5zbBpy881G",
	"B85-239": "G3EvuuRAay2",
	"N80-1176": "QRjWm92Cluw",
	"T66-1885": "Bzi5qxtvmgK",
	"Y85-1926": "lkrhPQykbk4",
	"K90-910": "Mr6OdS65fYk",
	"R50-1762": "Uw2udhjcaOn",
	"K00-783": "WCeAiSqIU8V",
	"K20-825": "VgZWcjvZlYn",
	"S00-1786": "PPSmzq34dBX",
	"C15-260": "L8oSP4WNqo1",
	"H60-602": "u1fiEWkF1xN",
	"L60-976": "tjsfulpsiUq",
	"I30-668": "Ofa8D7yrqwI",
	"O94-1412": "Gviy3f6fuSR",
	"A30-81": "ZvRWZxzia52",
	"I20-633": "Vvwr5kNR6tp",
	"P20-1466": "KSrBwgS4DQC",
	"N00-1079": "k6q38veDtlC",
	"Z30-1992": "E6n13aUjE9R",
	"K00-809": "HQ7mxpphr6V",
	"L50-971": "Qd4IPOLsyNm",
	"R10-1666": "C5lVXrQnMks",
	"L60-983": "puIoqLNbyN4",
	"R50-1775": "YZdqb8lHiAl",
	"R10-1654": "zdzVWID72U6",
	"S50-1813": "vlejd4JB1Vw",
	"F20-451": "yCVrr0wyrZZ",
	"P35-1493": "XHxad8Z3UVF",
	"A15-55": "cx83c9eVpOc",
	"D65-329": "OSg9z9wsxTi",
	"O30-1278": "yZweNVKF450",
	"B00-138": "IY5jCtY74mS",
	"C51-282": "Smp0fIN7XIa",
	"B65-233": "aQyNnUbxoY1",
	"O20-1234": "vEVIJRWPnFT",
	"E70-434": "OppqzPn8cws",
	"P00-1432": "T5CJ5zDodgw",
	"O00-1205": "ofBAG99DNpK",
	"L60-985": "pqXlybCd1DE",
	"K40-847": "Hs3mTTwb176",
	"C15-268": "PDY8HNEK0sn",
	"Z20-1973": "LJYUhAlv21k",
	"O30-1280": "WVy73xcVpYb",
	"P05-1440": "S4t3ppY7l8P",
	"J00-718": "OGQg3h2LB4R",
	"Q80-1600": "yhWqCrstRvm",
	"K00-790": "aldOj5dJRxy",
	"T80-1897": "Trq2tLsOcqS",
	"G40-502": "lIirog9aRYe",
	"R50-1772": "PShftz0I6Ev",
	"R40-1709": "Tco7HDCX4X0",
	"P00-1425": "hNC9qzgEDa0",
	"S30-1796": "HKRNk4tFmLk",
	"A30-71": "EgrUaMNg3CC",
	"Z20-1968": "pSb6WWDKRP5",
	"S00-1782": "NYIg79tisCZ",
	"E70-431": "zfC5gw4PtEs",
	"G80-533": "jkyzkoGQzmT",
	"B50-196": "rmqxJ1TtUEA",
	"M50-1055": "xUw2AyEr5E9",
	"N80-1170": "Mm3cXS5hk85",
	"M86-1071": "PfKeBJ1yC4y",
	"Q80-1599": "K2PRq3QJus2",
	"Z40-2038": "Y15nqlVPqUV",
	"D60-325": "n82u2hJWSLR",
	"A50-86": "xNsoETLcDLP",
	"H65-608": "uv7s2v5g4Tm",
	"A15-42": "AEoHY7MZomT",
	"Z40-2033": "TAojfyyzQBk",
	"N10-1085": "xxM9xVAjWgP",
	"K40-840": "LdAzOtrQB9S",
	"Q38-1569": "TPB0T6FAC58",
	"P70-1524": "XxQVqUUMPIf",
	"O20-1232": "BWFdsYSjdgB",
	"E00-348": "DobMdmQ5XwM",
	"I60-688": "qu37jAjk8rE",
	"F20-450": "RJTtVd8RoJy",
	"T66-1880": "EGLLLHN1NP0",
	"A50-90": "NL2XBYYF27L",
	"C76-292": "nnSPWAct3qn",
	"R00-1627": "OafQLvHinip",
	"R20-1679": "uBdtIhbytGo",
	"L00-913": "YzGac01N65w",
	"R10-1664": "c3J8zD7lz5u",
	"N80-1175": "zjucorIspva",
	"H25-573": "ftPdKXLYfKc",
	"J80-734": "ZhM4TcxePOH",
	"R20-1677": "BUZYIXH1dK8",
	"P50-1511": "WNZUbYK1ZQt",
	"K00-763": "QluUHGemXau",
	"F30-469": "hy5m1iOQVVk",
	"Z30-2000": "ggWWNsxqwuu",
	"K80-895": "QnS5z8uMKVk",
	"I30-655": "GEu1C3rZqNW",
	"R50-1755": "Mmvhl3EwWTH",
	"B65-222": "wAmqmJ64Rzi",
	"L00-917": "XhgOWRueg4J",
	"M05-1012": "Ag2thkz58bW",
	"G40-503": "Ivk0u3yKMK1",
	"I80-707": "PR2WogeY6y7",
	"B85-242": "XTtxapj0mhC",
	"L60-979": "FrcarvMoGI6",
	"J09-721": "oE6aZyKNX2T",
	"Z20-1959": "tNv4LrKrXlV",
	"A15-45": "PaKsIU8lcsq",
	"O94-1405": "HZAj4BIOunZ",
	"K55-868": "kdb412Y1o7j",
	"K00-792": "rNaxfkbiYSn",
	"A15-51": "WgdUN7FMqGh",
	"K80-894": "j9g90GUTY53",
	"F00-442": "wjRounmxFjZ",
	"Z00-1944": "mmVHVjlxP1m",
	"L60-984": "flOMP3MJGad",
	"O60-1346": "VT49tM7NMm0",
	"K40-837": "aWViYGynDwk",
	"A50-96": "O6GeRy0pxvO",
	"P75-1527": "SQuF6S1slAE",
	"P50-1518": "ec8KD7gHQCT",
	"K55-876": "CJFxJKVahbf",
	"N80-1179": "ppGR8toj5zY",
	"R50-1739": "fe6wexzqoda",
	"K00-803": "YElkijeQFmv",
	"N80-1148": "AQPLUYIXYdz",
	"O60-1330": "ZoclFyZVCkr",
	"R40-1717": "imVTzrZTUyF",
	"Y83-1920": "pfJbea6UCNh",
	"F00-443": "d080zdBWFHw",
	"P35-1491": "OutE0FbJAAJ",
	"B65-230": "jFhg4mVbz6G",
	"O20-1254": "hNt7mVKqH7f",
	"O30-1308": "oGnJVH2ISZu",
	"A70-114": "zO0TDcDamUD",
	"D60-324": "ICKsTw6c6tU",
	"A70-113": "fqQPpBKo7gC",
	"O60-1315": "fxQRRDL6djY",
	"R40-1726": "nfJKn934CBy",
	"K55-867": "BgS35moanoV",
	"K40-851": "wvFkphVHG5X",
	"L20-936": "StV77SrIpau",
	"B35-177": "xbeRfwzF6QN",
	"B35-193": "sEOZIJxPb2U",
	"K00-743": "xXYFxhAKKwx",
	"M05-1022": "kLAsNNkv2uB",
	"S80-1830": "aX5ywAKTP6v",
	"R20-1681": "RrDObyN9wWi",
	"K40-838": "u11Osy1w0zw",
	"E70-439": "L5nhmuXHaUl",
	"O30-1297": "BALahr98WP9",
	"L20-943": "e6iieTZwz6U",
	"K00-748": "hHGcvJRgFnL",
	"L40-947": "dQShyKAQxzE",
	"F90-488": "DT6Bqpu0FY7",
	"T66-1873": "j1YGF551u9B",
	"O85-1393": "px87LBDNY8T",
	"K00-810": "n7LN43LTpg6",
	"T08-1841": "wgti5ngDKW0",
	"K80-898": "lSW3Q31yLoD",
	"A50-103": "WU3JFBKHxhu",
	"K00-782": "PL4F1VthoDc",
	"Z00-1958": "kbh1iIWwW9T",
	"N30-1096": "FQ2uXl3cJQI",
	"Q50-1579": "uVlpkHfgiZ7",
	"N40-1120": "kVRBn0mLV4A",
	"C43-274": "QrititUjamf",
	"Q90-1605": "Be4rqFeE9tP",
	"L40-957": "gpJNjrykONN",
	"O30-1299": "vZ4WOez3uvk",
	"K65-881": "RaJ3laClH9y",
	"O60-1369": "pOijPPDmY39",
	"O85-1396": "rXN5ivP0WLB",
	"K00-793": "sUhxlSIMqWD",
	"P00-1421": "HLIyKfxBoVT",
	"F10-444": "Pw0qWtT2pmO",
	"O80-1378": "WrZT1dvHFLW",
	"G80-528": "ao3JNruHVs4",
	"K00-752": "XDSBU9AWxwG",
	"G90-546": "NUqeLjGQOlF",
	"F40-477": "jcDIPj44vYM",
	"T66-1882": "dermfYA8i4m",
	"Z70-2049": "reFxL7EK6rG",
	"P75-1526": "IyUY9fx4Z5B",
	"N30-1107": "Oxlol5yxRCi",
	"E10-388": "gT0RKDJu4OD",
	"Z40-2026": "szjWfilJRR7",
	"R40-1731": "FyyosLY6Lvr",
	"T66-1879": "RYAqjpnrL2z",
	"R00-1617": "EmkutR8PwW8",
	"K55-863": "HDbu2jbR0QU",
	"L10-925": "luLUVwNDz1i",
	"R25-1686": "PSM8aGT2yqQ",
	"T80-1894": "ruSVJ9V5KCD",
	"A15-36": "VM9BBpPmOv8",
	"K00-769": "Us9escuEqoF",
	"Z20-1970": "GqYwQvafvfo",
	"C76-296": "hV9uUh5LNzT",
	"A15-52": "NhEqp7mYyU8",
	"P05-1442": "AZ2OWy2XSgi",
	"E10-381": "qaOdC5PVEmF",
	"Z00-1941": "OTwpOK8cCj2",
	"S20-1793": "L9FCfsDofeM",
	"S80-1826": "akwbqZXkcGu",
	"O60-1318": "na2JFn4fEAR",
	"P05-1446": "dGyslxjuuWj",
	"M80-1068": "QXVkSWrRnfq",
	"O80-1383": "Uder1zOCGgV",
	"Z00-1935": "Dkbenax6IpH",
	"A30-66": "Utz4YLfwvvp",
	"K65-879": "RUiM3NTIoXA",
	"I26-638": "jrf3RxEonnC",
	"A80-121": "PICj7FyWNxW",
	"S10-1791": "XwfaIULs73O",
	"B90-247": "DW5riOvh9Nx",
	"K80-900": "L5WTYFORrVY",
	"A00-1": "MzSiqA0HdeP",
	"A30-77": "Jcf93XAmE1m",
	"R00-1622": "VUcBEHjfPaf",
	"L10-924": "RKmwMZ2tLcr",
	"O20-1242": "lNf2A92OYyy",
	"R30-1704": "WATGW4pCGpm",
	"A00-27": "L1YdV9D81NW",
	"T08-1843": "vHtN7CL8DVf",
	"M20-1039": "WE4UrxvxMRw",
	"Z40-2043": "z7R1psJ8uCM",
	"O60-1334": "GtMK5OJHBHE",
	"N80-1152": "I1Fk6OlEwxr",
	"L40-948": "sCFiZsAwPXu",
	"O80-1380": "AnQzygmAN16",
	"I60-690": "qTmck4m6OuS",
	"O10-1224": "CQJXH2uqVI2",
	"O30-1307": "rHAfWsWJktn",
	"K80-902": "ho1JOWBovBZ",
	"E70-433": "Bt5kjkV0c9p",
	"R10-1642": "prXMhEhKJMv",
	"A15-34": "qvTpAwIkBX4",
	"Z30-2004": "eBjvQHIH7OQ",
	"R25-1690": "jt4f5xxrlgb",
	"A90-127": "j0HevTsPQ3Y",
	"O60-1354": "vGH6gMRZ13S",
	"Z00-1953": "P6qGsarQlZC",
	"B00-145": "S4zQR4cfNne",
	"E10-396": "SDAn2Ko5DMZ",
	"M45-1047": "CAPdC3byO8b",
	"P90-1536": "JWUq4JlyXUT",
	"P00-1437": "gpKUgTvXXgo",
	"L20-942": "KDI5jrqXIUS",
	"A00-13": "EVhtOOmqqdr",
	"O00-1193": "gVWGaNudiqD",
	"P20-1473": "IX5ZNa4EOpA",
	"Q50-1581": "TrVnG2dZ6Pb",
	"F30-470": "TM6w1SjLC3Y",
	"A75-115": "bH8KUg64XQl",
	"R50-1741": "jUhgodUszxt",
	"A00-3": "Nl6x2gQ3uN6",
	"N40-1115": "p717DvSuHAu",
	"Z40-2029": "NAUKdfVN1fL",
	"Z20-1972": "vqbZpaXJlsk",
	"I60-687": "B85PsgRIsZY",
	"E00-347": "y1ceX7wQR1w",
	"P10-1453": "s4cqVRfnl07",
	"N00-1077": "dUhSJpXqxyH",
	"O20-1250": "fK7qwvqpuI4",
	"E10-386": "pAwVArUxwCf",
	"O60-1345": "Wa1XuXurAEh",
	"O60-1347": "GYEijgLVhoJ",
	"I10-624": "BybD2PaxOC0",
	"K00-807": "nq3fyIJIDKX",
	"L50-965": "NChCkYZCg7L",
	"M45-1048": "UJi138PuQ6G",
	"I00-611": "x0lbDPmNGT6",
	"P10-1461": "uyuBgBtZwFI",
	"A30-67": "f5ODvqsJT6b",
	"R10-1649": "WmL6jDxXB0P",
	"M70-1062": "FSWesapcVq5",
	"L40-951": "IMkdaCnA4f9",
	"B65-235": "YTDeeXp3bPd",
	"L00-916": "TxOgPVasSyj",
	"E10-383": "LPxelrwIBj7",
	"R00-1640": "lLLAapGZehE",
	"I30-663": "UnKA4SZXStE",
	"N80-1160": "WXnsWLLYIqW",
	"P35-1485": "aeyxeDBNiah",
	"R20-1682": "JjeGoLRkyzN",
	"L00-915": "eO4jBTfwORb",
	"O20-1266": "OxMJIjTQGbY",
	"E00-339": "dA3VEVWBz4y",
	"B85-240": "ee1yniVWOTO",
	"P10-1454": "p62ciUR513W",
	"K55-871": "K07gpMNfW0n",
	"O30-1310": "m0j9dD48jVP",
	"O60-1368": "xqv4E1ZUICP",
	"K40-839": "VXzuRJ9Wly0",
	"L60-987": "R7Ziqnsgm6k",
	"T00-1840": "FqcWMni8v00",
	"R25-1692": "KrFtHrt77Zb",
	"W50-1910": "PkqqBerJu45",
	"N80-1155": "SWg7b6z4HZH",
	"I30-666": "vRLTN5rE4MW",
	"I20-637": "K2s5KlRjpGa",
	"C15-263": "q0oWgFKDXiX",
	"D70-330": "Ld1kBpGS8uO",
	"E00-342": "NC7GyEMMn2D",
	"M05-1025": "QWT15R8dAKG",
	"I10-620": "bOp3xRD2RAN",
	"S90-1831": "FsGjTAJH9s7",
	"A00-21": "ECkjX1OtrW5",
	"A00-30": "vPJbrHMxKBC",
	"O00-1210": "Zt49s8Rci8k",
	"C40-273": "mi5nnOe3Ubt",
	"L60-990": "qofF7x4Foyq",
	"O85-1398": "npT1vaFevMx",
	"Z30-2003": "cAC6Oy2kNYG",
	"I60-680": "ajhyhtSlWbT",
	"G40-500": "pvZhCdyS9kA",
	"J30-727": "LCGa0r8WT1p",
	"O20-1262": "XJJfk46K8EE",
	"P35-1490": "SMtkoA8ngPP",
	"O30-1295": "Bxobhi3bGAT",
	"R40-1733": "zV6jrYdGizW",
	"H00-552": "SRZEyRupb4q",
	"O30-1302": "hM79L2Fffwb",
	"Z30-2008": "hkdbKNYc34o",
	"B15-154": "DrqTQokFcFr",
	"B00-133": "mV7fAdYblIi",
	"Q90-1606": "jZxZUBeN1Mo",
	"O60-1365": "k2QDU8bsZ9B",
	"R40-1730": "BryHCCWGl4F",
	"Z40-2034": "s0MHMIycya4",
	"S60-1820": "gpUcJddDZ8j",
	"B65-218": "JzQcZnRCZVx",
	"R10-1643": "tleiHfQ88C6",
	"E40-406": "LIx94eXDz1v",
	"P00-1427": "tJwJlAjgCpw",
	"A50-92": "fUgQUsEru18",
	"J40-733": "M4ORvNgVE9U",
	"Z30-2006": "rcLcfDTSL0t",
	"I30-647": "ftSjsB9acku",
	"T08-1850": "OE3EM3rCrSV",
	"K00-754": "xkKxTBUUmYf",
	"R20-1667": "BI4u5mehsYD",
	"O60-1319": "U8DOfuE7liC",
	"I05-618": "Zzvhc6ysWMy",
	"O60-1351": "QWIgNfYVMlw",
	"E00-341": "mWgHqgroIkN",
	"B15-151": "sP2f04edu5O",
	"Q50-1576": "FvXU5mD3cOV",
	"O60-1361": "FFEIA6rjE1T",
	"M05-1010": "kttjXwyK5SK",
	"B35-184": "ZSBy2vArDwp",
	"C64-287": "MZrdZK9nOYj",
	"Z20-1961": "yMa7rPncfvi",
	"O94-1407": "U7otDLRdsts",
	"E10-367": "j4tTJPnmJ6c",
	"E00-344": "ypFwu7qr8Qc",
	"A00-5": "ybEmrWicqv1",
	"L80-999": "vD7lolRc9ax",
	"N40-1116": "tcMl1nxOZXn",
	"P10-1451": "dosFa1wL2oH",
	"B90-246": "HEIVDDjGn8z",
	"R50-1743": "nZUlgFVjlA6",
	"E10-353": "GrAYmtoSLl7",
	"K00-781": "D2hUDpWSxed",
	"P50-1520": "igq3FbwRaVW",
	"O60-1340": "tmYlHqKOf5F",
	"R30-1700": "DXMw2r7ItBU",
	"N17-1087": "KiXFaIStlB3",
	"F10-445": "vGlfUpAOgRa",
	"S50-1815": "AyK4vCCCznz",
	"I26-639": "hpVW3oJozZY",
	"O20-1256": "PzZR2zzbyW6",
	"Q20-1555": "SDlSwYhbEcB",
	"Q10-1548": "TpWjcqarkY9",
	"B35-194": "ZeISfQGnHTF",
	"O20-1248": "R3JYbKIM8mb",
	"R20-1673": "u7V0PeySvaV",
	"O20-1231": "r9Dng3zhIk2",
	"P00-1429": "UJSxXanqFcp",
	"Z30-1989": "mzX0cipJBfa",
	"I30-646": "Qc8q9mcnwqr",
	"C81-303": "ZLp7lOaavI0",
	"C81-307": "yOF0sfGdzcb",
	"H55-597": "YtjwI4jfix6",
	"F40-473": "CEmiGITML3q",
	"F90-489": "rJfFHDR0v1d",
	"D10-313": "sQ4WB3KHWm2",
	"E10-377": "tXUngnZrN5l",
	"O80-1382": "foBxbwsYdy3",
	"R20-1672": "N8aDg3QQqqo",
	"T51-1872": "E2JlLB3uZNt",
	"P20-1474": "pzGH3nEhYNJ",
	"R00-1628": "dP0TNpy4187",
	"Z30-1991": "AxkfDHsp3Fj",
	"P00-1426": "MnBHYd1ckcE",
	"H65-605": "AhqbbplLMBM",
	"B50-203": "WvMqItWTzvZ",
	"R40-1716": "sMdItUegNaQ",
	"O00-1204": "yYixWAkzVnB",
	"I30-671": "Jq3x7MU7yWa",
	"A00-9": "trkZc8zEmBw",
	"R00-1620": "jImW3eQwxNV",
	"O60-1357": "lACCGSBgost",
	"P20-1470": "WzmNDjDzvR1",
	"R10-1657": "BuDXZUAYgYZ",
	"S30-1803": "kB6yajCfWfP",
	"N80-1142": "tRdrK1aHVMa",
	"O60-1353": "aKcR4pbtypU",
	"O20-1245": "qgY0HMjUdLG",
	"C51-281": "Wt6Fr2tjZyZ",
	"T15-1851": "d2SOkxQX7DC",
	"L40-960": "mmGAEm7zLEN",
	"R00-1636": "dbu2oiH35K0",
	"Q90-1604": "mdsntCkQj6K",
	"R40-1724": "avDcOKbTCHT",
	"I10-619": "W90JofUIjUf",
	"O85-1397": "muC9MdYnp00",
	"M60-1058": "JSdrE7IF9tc",
	"O20-1251": "UuRAvF053zn",
	"B65-215": "oQ9VbS7Dwcn",
	"Z70-2050": "waDC09q1sc0",
	"K70-892": "yTHfQLaKjag",
	"K00-798": "DhpVkvGPhxW",
	"Z30-1978": "B6f1aGWgnix",
	"K00-741": "bMToWunFXXf",
	"M05-1026": "d0iZlkDYooG",
	"Y90-1931": "aE1rgvVB9e9",
	"R40-1734": "kYdlVPGqECZ",
	"P00-1423": "qPn8Am9WRo0",
	"T51-1871": "chpvLALWW99",
	"G90-549": "wEnIOpaVFaa",
	"P00-1419": "SwOjburWY2g",
	"O30-1281": "klkOjdxI4HD",
	"G50-515": "A8TFm0USDUO",
	"R40-1720": "fLpXktSKon8",
	"O60-1364": "Y3vz3z6zXnF",
	"I30-641": "zcxaBb2HiN1",
	"R40-1732": "uJCDRXhUXhn",
	"Z40-2017": "jxB39RJfVu4",
	"K20-826": "zB2gDmNNiKj",
	"D80-335": "hCmBFK7tud7",
	"R50-1768": "QWZPYTYTyfc",
	"H49-590": "sKBM8M7R7SP",
	"Z55-2045": "v8BaFA9jF6z",
	"N20-1091": "r8U9inF25Nr",
	"L20-932": "TollORbxEF2",
	"F60-483": "uFEqlRpD2bG",
	"J09-719": "eDke5C9tera",
	"M20-1029": "ppbz05UrFQT",
	"T26-1859": "IcVhv4z2qvw",
	"I30-664": "PVg9FIGa3Yo",
	"I20-630": "BUNCvSJTkC9",
	"E10-375": "o0fTSvLmqW2",
	"Q65-1594": "oaCsyXDn7ug",
	"I30-645": "GZKQFEbdxxo",
	"O30-1306": "rTT79Uftgbz",
	"K00-802": "LARXq9fLiCD",
	"O20-1244": "Q2Eu6ZjdA9W",
	"S90-1833": "ZhGoyhG9jFF",
	"R30-1706": "N4S5zP5i82c",
	"S90-1834": "OIwl1amBbMV",
	"D37-320": "cxrg5Qw0fu7",
	"P20-1479": "sOt3Z91EQnJ",
	"A15-53": "Uirl6QZ9mzm",
	"P05-1443": "BgFtMQhdcWv",
	"M05-1024": "BnNTpdP1jCp",
	"M86-1072": "I4mE2wY9I9E",
	"Q38-1567": "pV1DGrTQ1CM",
	"O20-1247": "FZtNeyoZSm7",
	"Z30-1975": "m9xWb61EDFl",
	"H53-596": "nbRDlh3lnst",
	"T20-1856": "Y1atBajSkCS",
	"L60-994": "X5gEPcdBnzy",
	"C51-279": "sDfUX9f5LBy",
	"I60-677": "ODyImktsXHU",
	"Z30-1987": "XDCHRZctCbE",
	"F30-465": "mqJnWtvcQEL",
	"O00-1195": "DKO8FgRqC2V",
	"R50-1746": "MulyQe6xnp1",
	"H15-570": "IDQWnDn8To5",
	"H15-563": "ZFmhsBS9q13",
	"Q50-1577": "iq9Q3vbnlWH",
	"T80-1902": "i4xKRCrXxXP",
	"E50-413": "QZlr001mGvd",
	"R50-1764": "FckRht6XmLI",
	"B50-204": "GYZmBo0O4ui",
	"E10-359": "qjf6LiOBR8i",
	"O30-1296": "VEGibNe6lIT",
	"P20-1465": "ah7mLZm7pVW",
	"C51-278": "tCkJmEcGnS6",
	"Q30-1560": "mXaWODWXVKX",
	"T00-1837": "VuAuamCi86s",
	"N10-1082": "O38YUy05V9c",
	"K65-880": "i9Dn4vhYgLg",
	"T20-1855": "xhSgoK37nnu",
	"P20-1467": "pXQu8alSYfb",
	"N40-1112": "CVXjPQL4hBy",
	"P10-1464": "cLWuplln3B3",
	"A15-44": "jxwzZBoVbrX",
	"B00-137": "HTi46IHL6OX",
	"N80-1168": "KPQNZiLPbUp",
	"B95-253": "yjjMxJ77etm",
	"B35-185": "RIB0xKANjq0",
	"E50-414": "EmkJxAI85zs",
	"B00-150": "vJ9TFfurD0M",
	"L50-966": "uxwIt8Luik4",
	"A70-110": "XIFISIksU1G",
	"O30-1292": "Qn9jp4jiZPt",
	"R50-1753": "eJXtM8G33dd",
	"N40-1114": "RaESg7BHjnk",
	"C81-311": "iqoVyGWFOP8",
	"B35-188": "R7NMrdzr5e0",
	"P50-1505": "YW2HMiebtfk",
	"Z70-2047": "Ibk1ePBg4zE",
	"G40-512": "Wl8inzOPck1",
	"S00-1780": "vSymWgdxWYX",
	"I30-662": "O9sfTHHIMvh",
	"L80-995": "pgXd9ovvl08",
	"E70-438": "bosRmlW5wp5",
	"Q10-1549": "mvhrQyLLmvk",
	"O60-1312": "Z2m2S3BudXO",
	"H40-576": "bQonADB9MNZ",
	"L55-972": "jZzofx2hvjT",
	"E50-417": "YRTcyvjAjVH",
	"H49-591": "m8e3fJyHAHa",
	"B35-173": "EwLhFuNHBYq",
	"W50-1911": "xiSlrRWSe72",
	"O00-1197": "NIb2zvBaEj4",
	"M20-1035": "CnMvBp2SFxf",
	"C30-269": "QnDTOWDWO7m",
	"B20-163": "FTxbSmSF9HT",
	"R25-1693": "I1noyABddXj",
	"B20-165": "fGvVXA7IIu4",
	"K00-804": "IGXMVao5KSN",
	"E70-429": "GB6kPGDpFEU",
	"N80-1173": "urniKvuKvtF",
	"H40-582": "MpHWmErsgjg",
	"K20-823": "UzQzzv44vic",
	"E00-345": "ZfrT7z6JFAM",
	"N80-1153": "EP4Ll9ltyGM",
	"P20-1476": "NGdxDHb90i4",
	"R00-1629": "I7hD3X4Mn5F",
	"N80-1134": "N9av9dybLtx",
	"N80-1156": "woDiVThtIT7",
	"H40-575": "dAAmWG2ijqE",
	"O10-1228": "onl9mrOI64C",
	"M05-1009": "izjgwSER0GK",
	"K00-771": "zlGu8588gaI",
	"R50-1749": "E4prQA8ikKZ",
	"O60-1325": "zgTTh8iGsQP",
	"E10-380": "zN0vWEkB1z6",
	"O60-1343": "FsCxrT3WGTz",
	"E70-430": "LxQY4KHKpGp",
	"H40-578": "k73WfGKgKFf",
	"F20-455": "SrnqN0bIRSv",
	"L80-1000": "fHb6tWfnTRi",
	"A00-18": "L0xAdV0uCVZ",
	"H46-585": "Z8f1HHCNamB",
	"W50-1909": "bg7MVaIV0s3",
	"C30-270": "WlWLQEOfWRF",
	"O30-1287": "yRYcATaIBBZ",
	"B65-231": "co9oQSP5VVF",
	"M30-1044": "DI5eRCg93qj",
	"O80-1389": "rx6ZzRVps0G",
	"B00-147": "IjobptsUJuU",
	"S80-1825": "ZW4hjTZv0l7",
	"G90-545": "vXiiJzVIIf2",
	"N40-1113": "K9GezaTdqa6",
	"I30-659": "WiehN1ZspC0",
	"P05-1445": "FtWYXX9eVhB",
	"A50-84": "EiCbafGDpR4",
	"B20-156": "GfVCcVM4rAs",
	"N80-1144": "p9SsPRf1XbD",
	"Q60-1583": "BknENdH0Tlj",
	"A30-80": "St7pvIoQAXM",
	"F00-440": "an2o8xTkj06",
	"K55-875": "pgqyBqHai2m",
	"M70-1060": "jkBR1Ig7WHR",
	"A50-100": "iEOqoeLXl3q",
	"O20-1261": "zGhaPBmBF5J",
	"Q00-1543": "xieXd83yc4F",
	"I30-650": "qSkhB76XUFT",
	"B20-168": "pyIM83BWU8i",
	"E70-432": "hCYSEDgTbpD",
	"C00-258": "jUOkW1FIlbK",
	"B00-141": "VF4ZqLcap1S",
	"H60-603": "eCPlwC8YRFx",
	"C30-272": "fjgZsYxhEbD",
	"Q00-1547": "F7Cj9zxnW5O",
	"B00-143": "iiH0ddVXbtn",
	"I30-652": "qfSTuPOv4Is",
	"Z20-1969": "qleJ4D2c992",
	"E10-403": "RPCDmZJYuX6",
	"K90-903": "bBsIYQbfuZD",
	"H15-558": "WlNpKqdZ4Qe",
	"L80-1002": "dEokYZcK9WR",
	"T66-1886": "UVvc8mZc9Ai",
	"P90-1538": "q3Afxs7RG7W",
	"P10-1459": "j60GAj6qMFx",
	"E10-404": "suNoBoJz8zb",
	"O60-1332": "hUicWyEyMxD",
	"A15-50": "LcwlODgy9m2",
	"E10-402": "ISRmNXZT3Qh",
	"A50-91": "o3o5aFx6bo8",
	"Q38-1575": "UjPyJGKQxfU",
	"N80-1136": "usSgU49P66l",
	"O00-1189": "cMHSqlfXbEI",
	"R30-1705": "peDNDcOeA0v",
	"P50-1503": "PlzlX4rNXLt",
	"B85-243": "m4YfUv7wx8m",
	"O60-1336": "ciUPEGZjwaq",
	"I70-696": "Wbb3ncPADMa",
	"F20-454": "TVMkS9qLoTC",
	"Z00-1949": "gLurwAHfFXf",
	"K00-777": "lgsGqcs1xtD",
	"R25-1694": "b2JgxVa6UCM",
	"E10-376": "LfVznnr5avx",
	"Z30-1980": "rcXAotRSkAS",
	"P50-1506": "nOlpGbmlm3D",
	"P75-1528": "nCfubMXK8oP",
	"L40-950": "nkM9WKnTeuZ",
	"B95-255": "JhWp0QHIBhw",
	"O80-1386": "giOIeJHmr0p",
	"K00-767": "G7VPH1KtJbZ",
	"A90-130": "CW3RzXOoa0y",
	"E10-356": "RyCR8yLYaB9",
	"K00-746": "OvNcIzCMPEc",
	"B50-197": "moq6FPoeBDm",
	"R25-1687": "elBjunx8nRE",
	"I60-693": "Gb3AoeuFFL8",
	"S60-1819": "sUUBmH7We9I",
	"G40-493": "XSxp6289Bhk",
	"K00-817": "GeJyMviz286",
	"H55-598": "wJbSGR6uFCh",
	"O10-1218": "wC7ma4ULFA5",
	"S30-1801": "pn9RSm8yKrl",
	"H15-561": "EuXdgLuKmDY",
	"M00-1007": "rkG4VY7JHTw",
	"P35-1498": "eweFLSzatRv",
	"M20-1034": "FMg8MamqaZ8",
	"B15-153": "lcCMtKgMeiv",
	"B00-134": "Ld7W5VhjOtY",
	"J00-713": "XgStQIpl5tr",
	"A30-69": "kAQFLT7RxZT",
	"P10-1460": "IIfXyOv6AxK",
	"Q35-1565": "UEPmpgDAfQo",
	"E10-368": "vIQWRhzJni2",
	"L20-930": "O9KCufkxn2f",
	"S50-1810": "Ek7Kd9TCP4G",
	"L50-964": "AC0eS1aM7Dt",
	"O00-1215": "HX53HgeNPaN",
	"T66-1875": "qSVtImDUtix",
	"P00-1424": "jw7TwSQyn0x",
	"N80-1183": "zPTzixwfT0t",
	"R00-1625": "fY4b7IkF4dc",
	"H15-571": "cwIr9ZrzC7Y",
	"T79-1889": "SJz4V1BmG8I",
	"R00-1626": "dK8yQXx5ISH",
	"N40-1109": "SEMzifu12W7",
	"I70-695": "qhDCqV5Lc4y",
	"C76-297": "LlkC4e7Pm5N",
	"C81-306": "H80Yq3DPGgL",
	"W20-1908": "SHeGqKJRdf6",
	"Z20-1960": "Ep55m52OZra",
	"R30-1701": "F1PW8Hw38ya",
	"P90-1531": "xMghxfJ21yA",
	"G80-529": "kVEvjbH13VQ",
	"Z30-1984": "yNNuPHpkgcj",
	"Y83-1924": "iOIiRvDXnoG",
	"O60-1352": "PVc3SBiHGck",
	"P20-1472": "lPVduW01aOV",
	"E10-364": "zRFiIei7x90",
	"A15-49": "SRZFp3Jbtko",
	"C45-275": "L1MJ22gyrnS",
	"K00-759": "DM5wDsXOrBj",
	"L60-978": "oHlVbRnrQWa",
	"R00-1639": "qaAERXWDpeE",
	"Q65-1587": "wPDKmLr9hbK",
	"N30-1098": "pPP8HPqGhVI",
	"C00-257": "BsYjgYYUus7",
	"L60-989": "S8ydOtb8UfA",
	"R70-1776": "iGV4g8935EV",
	"B90-245": "cUa7YHOTDEh",
	"A65-108": "S70W5MdX0sL",
	"O80-1381": "gIBdAYLZARg",
	"F40-479": "H3ltMo5sbbQ",
	"A00-28": "XkQjFLs1LZK",
	"R25-1698": "XZbcGpwRPff",
	"O60-1376": "XGH3y61beUC",
	"L00-914": "tQSQO8faxpz",
	"I80-705": "wCLjpJnN7TD",
	"Q00-1546": "FRKAiAbhmjA",
	"O60-1313": "nTcGKhY2Ox7",
	"E10-389": "LetGVbZEgBc",
	"M50-1054": "bMSxTmcTGHs",
	"H49-587": "IKyhBbeOwAr",
	"N30-1105": "MsttRecsO8P",
	"K00-816": "WJaHDKE0ula",
	"O30-1309": "bfrNPkzzbjY",
	"H00-550": "w1q3djIrnbQ",
	"O00-1199": "AFX581FxjOB",
	"G90-547": "f0BJKC1qVQn",
	"K40-835": "X58L9nXeDu1",
	"E10-370": "vRwrPN618cf",
	"T08-1844": "gbhypqwYVgJ",
	"K80-896": "SkxZ0jKFKsa",
	"S70-1823": "B2SIHqil389",
	"H40-581": "PnVteYfq9R2",
	"K00-796": "lw6IWMi8jp1",
	"H00-553": "uSSFdBli0ZE",
	"A15-56": "mc0BzkDzcKG",
	"K80-901": "YII4gszfI5s",
	"B65-221": "M3THFJ3atnr",
	"P00-1431": "b6ZGjKSXzow",
	"Z40-2041": "AUJAzrbIFN2",
	"N80-1141": "SOSOMiHeA7Z",
	"I30-643": "XkSBndacgP1",
	"J90-736": "glG3DhmqtET",
	"O30-1284": "BVO9BXIuQIk",
	"A00-24": "IJQg2yCDCJ6",
	"B00-140": "iSrn2UB45PW",
	"G50-518": "RiSPf2V5v6z",
	"O20-1263": "pQl74J9IGOu",
	"B50-201": "ALQjhqZF6LA",
	"A00-32": "jxjZViLfhWM",
	"I80-701": "U0LKkSP11kn",
	"I60-681": "BymTmPcpXro",
	"O20-1236": "lVuvygTVFJQ",
	"O60-1358": "eAnSbs1nL6Y",
	"G80-526": "lbkBaCfEvLW",
	"F20-449": "LahZ4b11T4S",
	"F40-475": "Q8hJub7OaoH",
	"B35-195": "awVJQprCW94",
	"A00-8": "rsJfqpDrYox",
	"R50-1747": "aFL9AoS5cv0",
	"L60-975": "k0rtxO449tf",
	"O30-1293": "ZebTbvnO1zW",
	"L40-961": "JYxQUyAGY9S",
	"K55-857": "AEwVSApFggg",
	"P50-1507": "cZ2t2UIMzsd",
	"S40-1805": "vmoNKHnWqwG",
	"Z00-1938": "LWiIVoZzyOC",
	"N40-1121": "tbrPqLiO8G4",
	"O00-1211": "cjrlyyoFABZ",
	"T80-1896": "Kk86v6vrvmH",
	"I00-612": "FmZbTTDPYh2",
	"Z40-2037": "mEDIA3Itmot",
	"A80-119": "a2OYUI6Hy7E",
	"N25-1094": "SpJUVyf5BjU",
	"O00-1213": "ph4Vvd2ASih",
	"D10-317": "rADngXDsyTD",
	"T20-1854": "IYgzmUoxaDP",
	"M05-1023": "Ir7lsJQQpyS",
	"E50-415": "QqLmOnjiVkJ",
	"K20-822": "Zg80tsD910Z",
	"Y85-1929": "HG9CFJ9uDbB",
	"K00-768": "SRCULuqjjb3",
	"R30-1707": "v5f9niJqR91",
	"C81-309": "cb4gjEH83qe",
	"H49-586": "yFDKdxnErxx",
	"G80-527": "Kk02BROv9J7",
	"G70-524": "Bwg1rFvBgSo",
	"P00-1433": "uj2zTHmhOrR",
	"R00-1624": "vCLaOJTz5Z6",
	"M20-1032": "m64ysxV1Iqg",
	"Q35-1561": "VecY9XHd8Il",
	"K00-761": "zzpOJmDUXYv",
	"R50-1758": "hGlVZTBqRoT",
	"P10-1458": "Zl9kjj1Tue1",
	"T66-1884": "CyW4dk6AaZQ",
	"M05-1015": "csXM0TeBci6",
	"R10-1659": "E9SQSGPcOlD",
	"R20-1675": "mCUECACqCPu",
	"L40-959": "fHWnkXsVble",
	"B35-172": "hEy2lsBa6hT",
	"S50-1814": "Rg2Cuxu8zFh",
	"R00-1616": "SZJ4glSEb2I",
	"K70-891": "pepkoOn7zKN",
	"M70-1061": "F2pYxMJhteW",
	"O00-1194": "uP69Kn5UgHQ",
	"I20-632": "M4II2zjBqjg",
	"Y85-1925": "p8ulv2xdHKo",
	"L50-968": "NXHYhyvnSBL",
	"H53-594": "rqVuxCZBnz7",
	"O30-1291": "cFlulEeuKRw",
	"O30-1301": "SLcbN6zD7uL",
	"R00-1630": "Te2THNeuZkG",
	"M80-1067": "mYgm0K8pkQp",
	"T80-1900": "mKszKDG5tyx",
	"Z40-2015": "kPypTr1J0h4",
	"R40-1725": "SHzXhhiz7gp",
	"O60-1339": "jfoJGu1Y1yp",
	"Q65-1585": "qotZLrWgInE",
	"I60-685": "rFxjZSB1zu3",
	"L40-949": "O4uQxti8i8b",
	"O20-1246": "rlHrL4d6AN3",
	"Z00-1943": "ikt0OwCl9j9",
	"R10-1644": "k6MLeYBhF5r",
	"C81-304": "C52mfDyVkkh",
	"I60-682": "WWN4WzqZt0G",
	"A00-19": "p2GYrWQ07PS",
	"I30-656": "HEApOdFcNWG",
	"E10-354": "Md7VWfsUwNf",
	"T79-1888": "yzN6JK9XAmb",
	"A00-29": "pOiEUhxJfEC",
	"N80-1162": "NEcR2jb7Fee",
	"G80-537": "t89grgwKE99",
	"B50-212": "bkaYZkc2plK",
	"Z20-1966": "IuyW9MlATX6",
	"K65-878": "kzTHuo2TCYm",
	"R00-1609": "Obz6OrqCuY0",
	"T15-1852": "ooAPqJIQFuJ",
	"K70-888": "bDmTLkZJxrr",
	"L40-952": "yTCp8ja5jpB",
	"T08-1846": "pMltbWwyckR",
	"L80-997": "Itgv8ukjNbo",
	"N20-1092": "RSx63OsDKWz",
	"B15-155": "wALXeebwXa7",
	"R25-1691": "XlzSzzNx32C",
	"Z20-1964": "wXcUVXkh7Fq",
	"B35-178": "D3M8rAWa7Fv",
	"O85-1401": "nuJnAbwZoOU",
	"N80-1139": "sIddZLQFWBG",
	"R40-1722": "R9dVg3m0b33",
	"K00-744": "herawPktc16",
	"G40-506": "OZSBpORRaAk",
	"K80-893": "Gyc1Z2QEQCc",
	"B50-207": "Cj2G6jiV9O4",
	"K00-815": "n9QTneVkgnN",
	"M60-1057": "CTPKNhnTuuW",
	"Q20-1550": "dnJkTrQREYz",
	"E10-387": "NQkWuDov9Wp",
	"B65-227": "PJRAMxbwIgq",
	"H53-595": "jVLcsPmANc9",
	"R00-1632": "TYtHjP8eArM",
	"O30-1272": "dZYhYb7CsiK",
	"S00-1783": "cCYvEyzC82E",
	"A90-128": "dw4yehMHuXb",
	"O60-1314": "tzsHBWmdrbH",
	"P10-1462": "vtGYqdRvmgp",
	"O60-1371": "hw0wl7OIAMt",
	"L00-921": "FhgA35y8vY3",
	"A15-40": "mGKRVdnaTHJ",
	"I30-661": "tOP3lpxvlBu",
	"Z40-2012": "CW031pk4LXF",
	"P20-1480": "lGmKE5bsvZx",
	"L10-926": "vrjN8pnjN6b",
	"K55-859": "QsIZCeO5uFe",
	"T66-1883": "PpTgSdIsKxn",
	"R25-1684": "znhHlBJe2xR",
	"L20-933": "FFIYA2DWayM",
	"S40-1806": "aFAjLhmE4Tc",
	"S60-1818": "uDnl3RGdUnC",
	"Z00-1939": "qaQMN3mD1mh",
	"O60-1327": "EZrNxYcdqZi",
	"B90-248": "CaWjazxYwle",
	"R30-1699": "G7c3nXamuTo",
	"N40-1110": "d9ql9s5xkDB",
	"Y83-1917": "Gi1IvARy5xK",
	"R30-1703": "fiCvbAfFBcD",
	"O60-1326": "et6xmt51VFr",
	"K00-791": "x0CZBydCheD",
	"Y83-1918": "B8xvnS8xo02",
	"F30-471": "EeLJdFKlHYR",
	"N80-1182": "Cv4J7RoCuXp",
	"M50-1051": "By8vSMRVRxZ",
	"S00-1784": "mDz2iFyZJhW",
	"O80-1391": "tMBSThKN04J",
	"T29-1864": "IqwYndlQzp7",
	"P50-1516": "Z9HqZjQ9xdR",
	"I30-653": "ikqvZ9hb7Vb",
	"P70-1525": "yHRIC87dc32",
	"O94-1410": "Uy3sUGYDocU",
	"Y83-1916": "oav4Et8UXnM",
	"O30-1303": "IEjeuIGU58m",
	"R30-1708": "s03IL3fHqwb",
	"E50-424": "EROkZGBFOMD",
	"K00-789": "fmwqswbJsBz",
	"I30-642": "YmDKwF4p49F",
	"T80-1899": "IjFD88xRmFb",
	"A30-75": "nj5PIxcrFBy",
	"H60-601": "ZaMI7i7gNYp",
	"N80-1149": "j17Nz9wbFrq",
	"B20-169": "wiU62mfHUKB",
	"R40-1712": "wVMQ2ccQLJP",
	"C60-286": "f5A7uKZdsas",
	"O60-1342": "ewVEPjYGI8E",
	"P90-1534": "AYHwmEBeEQx",
	"G40-499": "CVBtou5PNKi",
	"P00-1418": "gwuUifMlCxO",
	"I30-649": "gNOlVvxA9FO",
	"S30-1799": "iC4hcVu0cf7",
	"K65-882": "ve7T0hhMa5w",
	"O30-1304": "h3FOEwXcj1R",
	"N30-1103": "dxFYi0Z8pw6",
	"P80-1529": "WFsQt5IfJMZ",
	"L40-946": "PsZoAWLvVmY",
	"E50-427": "IoI0ekKFBlO",
	"Y85-1927": "UTu2oeC7VBB",
	"B20-157": "PGxEAqVKQSA",
	"P80-1530": "VXP3ZqbmgH4",
	"O00-1190": "PYcOee7gzBZ",
	"H00-556": "EdUgyT4talW",
	"P20-1469": "oN465sBx5Vu",
	"P05-1444": "rfm5uOaqIr3",
	"O20-1265": "jVtnCYPDOV9",
	"P35-1495": "T2Kl92XFJAL",
	"N80-1157": "U9i6SGiXbnJ",
	"N70-1128": "JxXwSJxEbXH",
	"N30-1106": "u9tY5aqW251",
	"B50-206": "TX48U65Z0Y4",
	"Z30-1995": "Jmz4P4VX3J7",
	"G40-513": "GayDPpa2keB",
	"Z40-2027": "jQtQjuCQA2g",
	"P00-1436": "TG0SiloDn6W",
	"G40-498": "OrhsBpqDWSS",
	"L60-981": "N55yYzLsZqB",
	"L80-1004": "CUozBa5hrFR",
	"O60-1367": "NgRvviRAUDt",
	"O94-1411": "Y1afKMsExcC",
	"G40-501": "NilOn4wuham",
	"L10-927": "y5uQGHSKItT",
	"E10-373": "Ok6EEVBha6L",
	"B85-237": "WYe8IhOzq7v",
	"A00-2": "TLF6P72XNP5",
	"Z80-2053": "G5r4XZJzSxz",
	"O60-1335": "YnuX0BUaWBw",
	"G60-519": "t04aqetAUjT",
	"L40-953": "QTIrIpASjUV",
	"P00-1414": "j27xLM4OmA4",
	"J90-737": "A49H6pX9fRn",
	"D10-318": "L9UKTBiOi8g",
	"B50-208": "FBNBlQL2pAe",
	"B20-161": "SuvmaZYeFuh",
	"A00-31": "BE8z6733JHp",
	"T08-1847": "UjRwZ0BVsjn",
	"Z30-1993": "T5gna2TEX32",
	"K00-755": "ySPqvhjTl0p",
	"C50-276": "KI2VzXfWlzi",
	"Z20-1971": "jKfx90M4vDN",
	"M50-1049": "nsKu1ZoBy2F",
	"E50-420": "eFljUlO4EV6",
	"Q38-1571": "nBZPkypL2X3",
	"A80-124": "rlvLJWsYN3S",
	"B95-251": "njamUdxAedx",
	"V80-1905": "rGFjnEQgFbL",
	"D60-322": "AATacrCpyta",
	"K70-886": "FFMNdTYfEVy",
	"S80-1828": "FsbTJwS3q3v",
	"T29-1865": "bOrxsgeLREa",
	"A80-123": "K2AGIBFK5vT",
	"N80-1143": "GsnrtzYVCxT",
	"E10-393": "xTmWPeu35PA",
	"H49-588": "d4cn5AR2Jv0",
	"I05-614": "ibh0NqRl539",
	"Z30-1994": "JTm0SnNGjms",
	"B65-225": "HpB4N2A76ed",
	"A00-7": "mvrCaGd5wHx",
	"R40-1718": "CFVFFg1vzeq",
	"E10-399": "Y2iLMrVZUsO",
	"T80-1893": "CvNPwxaUWVG",
	"R40-1728": "PRiRVKQwJJc",
	"B65-224": "O7NhykrxnsH",
	"E10-401": "eM9Qdn17LE5",
	"Z20-1963": "Xkh5LV49fVU",
	"P00-1413": "SGfWzd9YDum",
	"Q30-1559": "RSUSzGMo5mD",
	"K35-830": "UvpzfG1bLmR",
	"Z30-1974": "ZNqnYsUxAAo",
	"B65-216": "SueExX6qvp8",
	"Z40-2018": "J2WnMBsa27q",
	"K90-905": "k9zYfQWklMv",
	"T08-1845": "ZAGjI2tvjzj",
	"R50-1738": "u886Tj56skt",
	"I60-679": "klZ7WBIuvFA",
	"O00-1209": "lI6igAOZSkx",
	"N80-1154": "KrcnEiOSoe2",
	"E50-421": "QxKIF62DJ12",
	"O85-1400": "vQvJDlhbQe4",
	"G40-508": "lFU9hQbjXdb",
	"L20-939": "y9hLZZm4E21",
	"R50-1774": "enYRAPPWHX5",
	"N40-1111": "t0AjNul8G3h",
	"Z80-2052": "y5CMu8f2dGZ",
	"I30-648": "eWTPEZzVLIg",
	"S50-1812": "f1tLSiD0VLL",
	"A00-14": "Ic0c3m8HPWi",
	"J40-732": "ciyG9qNzBMP",
	"B65-228": "dYCdfoOJWW7",
	"R00-1635": "C6FMzq9d46C",
	"G80-535": "zMGqWQIlJrq",
	"L20-931": "fjP862gpzlX",
	"I20-628": "XJmxf5Cb1vs",
	"P50-1504": "XwQPNfzKthH",
	"S00-1788": "OVRDFF80igz",
	"O20-1271": "dnRWyKhC0eR",
	"T20-1858": "f5uhTT216ew",
	"J40-730": "ZNpTfNQMJTq",
	"M05-1013": "qbZ3ENUsilM",
	"G90-543": "uMx0zYaVDPE",
	"P35-1497": "gHoQEcAIztX",
	"S00-1785": "t25Mb9o8wwX",
	"E70-435": "EQN7LF1QxQe",
	"E10-395": "l3qgWUwgTBF",
	"A70-112": "mpEMkQHtJiO",
	"P50-1509": "MeG12Ow6GmH",
	"S30-1804": "SgyubbpGAI1",
	"Z30-1998": "weJvzEsHWWX",
	"E10-400": "oi8Lk3FaPHw",
	"N17-1086": "s8qbTwOSOeg",
	"O20-1249": "q1ruBjp1W86",
	"P00-1422": "WNmgUUvNncc",
	"P50-1508": "vR3syIR84mH",
	"Z20-1967": "Oa57vt8ctYJ",
	"F60-485": "jQKbPU4fUGd",
	"O30-1277": "dgvLt3unKEg",
	"K00-750": "hqkGuwGWDed",
	"L20-934": "UJBRZkJl2dr",
	"Q90-1602": "RzgjN0ZBjvl",
	"J09-720": "BPSZF4Py8ZV",
	"K20-827": "NWrzVNJjvnv",
	"A00-15": "WWRuDKVZZdw",
	"F80-486": "cZgbnTA3IRS",
	"R00-1623": "TmkGIrK9Tl6",
	"E10-385": "sQvGdNFEj2M",
	"O30-1274": "H4HHlmYUxme",
	"L60-993": "vqg8n7h8BA4",
	"O60-1366": "yUtNYr15R8f",
	"C81-302": "s9GBjsXHogU",
	"I30-675": "gID9VSe79el",
	"K00-745": "RRIOvu4RkNn",
	"O20-1260": "exYKyX860Wq",
	"O94-1408": "XfkilS4FUL1",
	"P35-1501": "nkA4x7PP7Mx",
	"B35-189": "ewni8F4ebRs",
	"I10-622": "WjK4sA3D9yC",
	"N80-1174": "jvAXephe52A",
	"L40-962": "eeydqjey5nE",
	"K00-818": "tAz4oY4AF3V",
	"H60-600": "JCD77WmM7ek",
	"L00-922": "I90EOM2P325",
	"M30-1043": "aePojLWxR42",
	"Q80-1597": "U9gCtLyJwOf",
	"F20-456": "R1iffkBySci",
	"E10-398": "LFw5DzG0nh4",
	"Z30-1985": "CP4PUeHUlIS",
	"A30-82": "rgb4WB0aKPq",
	"Z40-2020": "THb3O97DS9f",
	"T00-1835": "OXiNLq9l9vv",
	"O60-1359": "hvmd9ctSua6",
	"A50-93": "qrR5ORwopaG",
	"M30-1042": "gr6CJB52dM8",
	"S90-1832": "TPygRwNpSX0",
	"O30-1275": "nB43hx9YvT5",
	"J00-714": "hAhkwloxmvP",
	"E00-338": "nVtgVk4Z3WN",
	"G70-522": "zDiITYld6cY",
	"R40-1721": "HP8fryzfjSr",
	"Z00-1951": "ZCtf9Q2mIO6",
	"Q38-1574": "NM7KuhHrgNy",
	"F00-441": "oPvOGClXr6I",
	"O00-1201": "wAST3KXZgxp",
	"F40-474": "oWRGIiHY1qi",
	"R30-1702": "Emmiv4160B4",
	"I80-704": "h71cOxquBjo",
	"Z40-2011": "DNZfDAGekNG",
	"T80-1898": "KVWsEnrV4Ed",
	"C15-267": "W0qFRr34yhc",
	"E10-392": "vMlozdX07wt",
	"M20-1033": "d7mHbNYoflf",
	"E50-422": "SfuDCyh7PE2",
	"A80-125": "fAfVKl4e1YN",
	"C60-284": "glgOglgYSFS",
	"A75-117": "YCFfras0atn",
	"Y83-1915": "gtOpLsLXXfv",
	"B00-136": "snZ0phxhqif",
	"E00-343": "Cu8pCd8a9Qs",
	"D70-331": "E8aNUXaYmaq",
	"H15-567": "ecclpPs1avM",
	"O60-1356": "o0VKXcMiHAd",
	"A30-83": "kXv6TMg3TLA",
	"M05-1020": "bKXr9hNSUWd",
	"F20-448": "TKVBhjkywfu",
	"H15-568": "bC8rHmACY4Q",
	"R50-1760": "Ws64Vv7GMU3",
	"C76-291": "R5izva620ld",
	"A00-22": "UvKDhrSzt4n",
	"B90-244": "brvOTYQfNnX",
	"Z30-1990": "mnGdWPJLaf8",
	"K40-846": "QkGc4gNAMs2",
	"N80-1164": "YhmS1ORTAqr",
	"H55-599": "y5ZSuYAytya",
	"T80-1903": "ixsqDHwAlei",
	"P35-1492": "lJ1Hpg5z960",
	"R10-1645": "IlrkPVgqfK4",
	"L20-941": "cdFWdtPGxO5",
	"N80-1145": "ft7Rd4COkkX",
	"B35-176": "oDZmwDj7xxb",
	"N80-1150": "QIvmetnAhxM",
	"P35-1487": "vFvwOnhfXMb",
	"L00-919": "QMGPRtcp7jm",
	"I05-613": "QWy9sESGcg0",
	"Z40-2024": "IwpcYvU0UUo",
	"A50-95": "GpGT5aOZkej",
	"Z40-2014": "tRcDLyghvVX",
	"G40-496": "L12VE2YIgdY",
	"A15-58": "EOe0pwYdJ6m",
	"R50-1769": "RCDXsOFHWiS",
	"Z00-1947": "T6CGniT87bP",
	"R50-1759": "mArEODpICES",
	"B35-174": "qRww5prm4zi",
	"R00-1621": "Esw0wwql2zW",
	"Z30-1979": "y0qNfupXqkq",
	"A50-98": "L1PPNaW2SeU",
	"Q35-1564": "zWRnnjqAQkC",
	"K00-813": "v056mkPvZQo",
	"Q00-1542": "U8SqAafd7Zf",
	"G80-536": "Ll47ZQbCAAM",
	"O10-1227": "il18oInXFKx",
	"T29-1862": "JwRFVu7cSaz",
	"R00-1611": "y0p929G8v4i",
	"A15-43": "dFx9I1TELDY",
	"I60-683": "zxBBUofSHuy",
	"R10-1651": "ZNKlEfzdUjg",
	"C15-261": "vTP5pJWiY4m",
	"S60-1817": "cCrqMlip1LU",
	"R10-1660": "dTwB7Hk4gFY",
	"K00-784": "Gr9zeVAu0cc",
	"P20-1471": "G0qScrr5Ime",
	"D10-315": "KUwoHaPRZes",
	"A65-104": "Syt63waNOGD",
	"E50-418": "qIsK3Mw7liA",
	"P35-1494": "brCOaPWrHuy",
	"K00-747": "N4S7bKsdPg5",
	"B65-213": "LDMWDRsjaDH",
	"H00-555": "uQSq034Zjvc",
	"N30-1104": "Fq8KLGwLHuV",
	"E10-358": "X1ZlBrryD1n",
	"I80-703": "wzkpL7ASObH",
	"O85-1399": "H73VsUhGxGm",
	"L40-954": "k0S0IVtauV1",
	"O00-1200": "S7ECN6Q2uPP",
	"T51-1869": "e6iqZZNLt5t",
	"B50-199": "z1mnnlpCKew",
	"O20-1253": "EkNgBXGmizi",
	"T00-1839": "Q0Q6JcpBTQf",
	"E10-361": "mM9tw7PRJYS",
	"A50-102": "tsvu9Bpenzt",
	"O00-1212": "Ee5Q3UT5RQo",
	"N20-1088": "T4bCa1I0YeL",
	"K00-787": "BoYwgFgwEKy",
	"R10-1665": "Ns5ND6f3hOL",
	"I20-634": "Ji8Gz4XDZSa",
	"B35-182": "SFyJk5XP6jR",
	"Y83-1922": "VNNZStvrcwa",
	"F30-472": "ZQsMnuvu7uz",
	"J95-739": "YhEOGT2tm9O",
	"G80-534": "PR4R0jvkgCi",
	"O30-1288": "j5cvFF1MJDE",
	"Z40-2031": "Llj6kKFlub7",
	"T00-1838": "snztNfn744W",
	"P70-1522": "wa4fBhrbKmr",
	"Q65-1584": "T4NwUT1IRKi",
	"R25-1688": "DuMRjudYXPq",
	"M30-1045": "FsQneQC5oFm",
	"Q50-1580": "DjFPEEYShz9",
	"I60-676": "oZyRI4veuSJ",
	"N70-1131": "AihWgf5yKml",
	"I80-702": "fQySVnFlo6Z",
	"L20-935": "Ub0MiuDfd9R",
	"F20-452": "OhcNxBugAfP",
	"J40-729": "F9nU7JyfXCN",
	"H49-589": "cpxJUCcXsJb",
	"O30-1290": "RWulXW939kX",
	"K00-799": "TpVnRnsWvyU",
	"K00-788": "SOX53JJ1oBN",
	"R50-1756": "Ec0ciVwF8Qh",
	"L10-928": "DPQ7jby1vH4",
	"N30-1097": "H3BrWjuNxUJ",
	"P05-1448": "Z8tMDMow0Vn",
	"O60-1362": "eEwcjuoqvnx",
	"Q65-1588": "YPzffYsT0uH",
	"N80-1147": "VvrqBHJIIaX",
	"N60-1125": "c9FVvvwvBD5",
	"L40-956": "AhdZpIGWHhq",
	"N30-1100": "XqQxJrWK7Zz",
	"A15-37": "xnDhimDvJQk",
	"T80-1895": "uGmA14WjZw3",
	"L00-920": "MqitMJykdhX",
	"R50-1745": "Qsu5G3Pz63i",
	"N00-1076": "WHzoKrz9FWU",
	"B00-148": "zZIm7G3Ycac",
	"B35-183": "aG5vecI5CLJ",
	"O85-1394": "WyilvKoLgcg",
	"M05-1018": "n7JU3W003v7",
	"K00-805": "k3VsseYK9Q7",
	"C51-283": "TxmS3r07f0f",
	"S40-1809": "O8gKUCcZN2r",
	"Z40-2028": "QdRnrJ6eBcV",
	"Y83-1923": "LGAEzYXeUKk",
	"Q90-1607": "nrBGogHtkgn",
	"N60-1126": "FQto1CCYOou",
	"S40-1807": "z071S3BWO6K",
	"Z30-1996": "cuHh2AziiSA",
	"L60-977": "yDquJUrsJ3Q",
	"C76-298": "t7x8Kv8zlCs",
	"P50-1510": "O9kuknwKFM0",
	"K55-861": "NGHeBW1zOGH",
	"Q20-1551": "cOa51lXVRJt",
	"M05-1016": "JfvY7syJl8o",
	"A50-101": "KTr1Gify5Ox",
	"O10-1223": "T269kPxN0G9",
	"M70-1064": "sNw4sqUvo8y",
	"B50-205": "dyAkT4K1ynp",
	"E10-390": "Np0JJECUb49",
	"N80-1135": "X1IgzkvY1jm",
	"Q20-1552": "oZtbZLKbzoS",
	"P00-1435": "XGEizRviXSi",
	"B25-170": "WaKYispTFUp",
	"O60-1331": "UNYVmVOVPzd",
	"O80-1384": "YtxX5nCWhbG",
	"C15-259": "fEIWHkZCwup",
	"Z30-1976": "D1gRtdO7FJ2",
	"K00-814": "aiKlasi85wI",
	"K55-866": "fbCnmQX3srP",
	"K00-770": "Ef5oRmDFe3g",
	"R25-1689": "Rn053tLf9SK",
	"Z00-1942": "k3XkAkr8B2C",
	"O60-1374": "o95NcYX0Y8M",
	"Q65-1586": "IOPZh4E9xxb",
	"H60-604": "kp704a1zqqs",
	"H15-564": "uIXQd0x8OXO",
	"O20-1264": "X5r4gjJC924",
	"H15-560": "YAWXXA7E6Rz",
	"E10-372": "sonhzfSx2AM",
	"K20-829": "nXyCryuzRHd",
	"O10-1225": "NX3tXatAQBk",
	"Z70-2046": "PlDvSAvvTMz",
	"O20-1258": "eLRv5LpyuKm",
	"R40-1727": "FeNnRBi7dyq",
	"H00-554": "ERSgJ2CeBc7",
	"E40-411": "QhxQu1uclTG",
	"O30-1283": "JqhMpIe2HMN",
	"R00-1619": "tgl6bX1srnR",
	"K90-911": "a2iOWdH0tYD",
	"A30-64": "CDbfxB1dCch",
	"Q35-1566": "NjNzkvlQxM1",
	"E00-336": "RsyvghNXbly",
	"K70-883": "jJXArpFDHck",
	"N80-1172": "tOFC7Vn7Yec",
	"H15-562": "pCWmh5C6jPF",
	"E10-365": "CHs3q9ou4I8",
	"R40-1719": "mAvz0E50VSa",
	"F30-466": "oLaUYnyS06g",
	"O00-1214": "WWHh1bIE8UN",
	"O10-1226": "lF3iQ2up9a9",
	"F10-446": "vaVmNAb2Hrn",
	"I60-678": "UZG26GyaWrO",
	"J80-735": "dDWtXeDiGg9",
	"S20-1794": "ELV2uW6c8vp",
	"C15-266": "tRaQtheJEz3",
	"L60-988": "Nulnz2JCQ42",
	"Z30-2001": "VLprnTKz1CS",
	"K40-850": "f8abHiIrNHc",
	"K70-884": "e9IrUOaeRUi",
	"O60-1355": "dQ9ZONjeTuz",
	"R47-1737": "JyoREELM11c",
	"L40-945": "LLdwponp7eD",
	"R50-1766": "wV26gRA2xrF",
	"A50-97": "pvj7fJmiquW",
	"T08-1842": "NIfJ3LsZD9U",
	"N00-1080": "CUeQhg5FkyZ",
	"A15-47": "dWblvLrlsgG",
	"O10-1222": "NUF3NV7WZIC",
	"B65-217": "IdAeJHdlrAy",
	"E50-426": "Hq5624L21AV",
	"P50-1512": "m2hyaTEBEih",
	"R50-1767": "jJlGGSsP8Bc",
	"M50-1053": "lXDmPeQ7Iks",
	"I20-627": "jAlghOd1xf3",
	"Z40-2044": "mmGtdIdG5Od",
	"A15-41": "cB1tzOpR4xO",
	"P05-1441": "OywG8raEYDZ",
	"G60-520": "X6SbrDS7mI8",
	"E00-340": "JXhkQ2Ev1sZ",
	"M20-1031": "rJx6QjjdIbL",
	"O20-1241": "tKasy9zd8zl",
	"T80-1892": "tF5hZlb2YlM",
	"F40-476": "BGMnhzMzKGa",
	"O80-1377": "pn909WJeNi7",
	"O30-1298": "YUjckfsJSHn",
	"A00-16": "tllsGJOrcSg",
	"Q90-1603": "tWMjyfS3dx9",
	"C76-299": "eP8QTXqguBx",
	"P00-1420": "RWdYmaSvPEn",
	"O20-1267": "L9SL0p4ZWVC",
	"K90-904": "fsFhHCEXMAD",
	"I30-673": "OnXXNAreDOH",
	"K55-865": "mj2aex2A3zj",
	"P00-1430": "VBvmt8Oo0z6",
	"B35-175": "BToADQFsTBD",
	"G60-521": "zSYqtQe57pX",
	"R10-1662": "adzHBODzYV2",
	"Z00-1934": "OHONYQa8cPi",
	"O85-1392": "rFd5cJ3Yk61",
	"T66-1881": "ZegO35GgsRP",
	"R50-1754": "lWkySm7DPof",
	"J30-728": "rPIjuQWGXpt",
	"M40-1046": "LKZ3PSgSb3Q",
	"K00-774": "tScqp767XC1",
	"K55-862": "ACWeubyGVzh",
	"B35-180": "kDS9IWdP3Hp",
	"R50-1765": "FVxEnUVbSAd",
	"N80-1180": "UOL4KrvUOuj",
	"R10-1647": "sAd0FMrYb3e",
	"K00-764": "k0R9mrDSwsX",
	"E50-416": "QksAogYZnwJ",
	"K00-753": "CIpYDdlnh4Q",
	"H15-559": "aDys8JWo1iq",
	"P35-1488": "AtyenM5pkSX",
	"O60-1375": "aLTaerrLuNl",
	"O94-1409": "J4WbkE4amvM",
	"Z70-2051": "QeGQEqEsQXY",
	"O20-1235": "zoMIFpGU9Pc",
	"I30-665": "TpRKux4lNWT",
	"C76-294": "VFZ0VSMDqV3",
	"O20-1269": "V8KOqoXcMAh",
	"Y90-1932": "eoiXRlRQkIJ",
	"A50-89": "yUflt0ac4Lv",
	"O10-1219": "H0rGsup5IKd",
	"P20-1478": "ddPQIZKWo9e",
	"B00-139": "UfjwqWnXeTH",
	"N80-1166": "nhyf3nNNKAC",
	"B99-256": "haTJZEbBPbk",
	"K00-808": "rH9KY2E8oVF",
	"G90-542": "x9e4FhJPbmF",
	"B65-229": "CDLbFM00Bw4",
	"K90-909": "zyMZldRYZht",
	"M20-1036": "YLMYJ98hpp7",
	"B85-238": "v2P5X6rlc5Q",
	"H00-551": "TgWDsDtXjqk",
	"I60-686": "EpSqvc2Ei7O",
	"I30-667": "UCexE13znwi",
	"K50-856": "y9anNENRbxK",
	"P50-1514": "MPaa4s0fXVk",
	"B00-146": "ipsdrrD7rG0",
	"K00-786": "P2qp1xAv5MB",
	"P35-1486": "hSoAIaNAfjC",
	"Z70-2048": "IaBorMlQLtA",
	"O60-1323": "ttigGQchKjR",
	"J20-726": "f8bfYZ2GbhJ",
	"G40-505": "P3sE9wu8L4z",
	"N30-1102": "yQAz1LOv75U",
	"O85-1402": "hXKvK7gZe1f",
	"K00-758": "WqCSVkC3K1j",
	"I30-660": "ncGviPd64ll",
	"T26-1861": "vmXvv5KFqs8",
	"N80-1178": "DSE4VWw4uf8",
	"R20-1669": "q5mQ3yubGPA",
	"Q00-1545": "rc5wFAybsJR",
	"P50-1519": "zEqQvLAmGdM",
	"T36-1868": "CckwLccp0Pr",
	"J40-731": "jETGiY3bstr",
	"K90-906": "mjzYwjAL2T2",
	"O00-1207": "f1vdHhXJC8y",
	"A65-106": "GICc0yn4kcY",
	"A75-116": "oEoYgamJOsu",
	"R50-1751": "ADr36KelJUP",
	"K40-848": "rkFUsOg8jid",
	"O60-1311": "FDTfcU6kqcY",
	"N80-1159": "WQqoOuRVphm",
	"A15-39": "qIPLMQEN7p6",
	"E50-419": "gXYP2oRixab",
	"J09-716": "j3P4TLsT5US",
	"T29-1866": "DsZxawlEe9D",
	"Q38-1573": "bwHGuo5ORrw",
	"O94-1404": "jvyjSeW5RXt",
	"N80-1137": "PV3qk3Pq6YT",
	"Z00-1954": "WSOZfaf19SR",
	"O00-1192": "uKfkzAe8Jyx",
	"N40-1119": "wVvmKPgVwfx",
	"M05-1011": "qbdUpCsPumX",
	"B20-158": "a1Muq7os6JZ",
	"P00-1428": "QLglid7ii2e",
	"A65-109": "a5vPvmdj9k3",
	"T26-1860": "xJUyoF5j8OM",
	"F40-480": "B487DJy0Bn5",
	"B65-223": "XihDh5PAhxi",
	"E10-384": "mYkhOFptHoK",
	"T29-1867": "dKcjm59uvnQ",
	"H25-572": "oRg3bkG8tHO",
	"E40-412": "BRArjp9sEOB",
	"C76-301": "octtDVCOjNS",
	"O60-1363": "pqqd9bBq8y6",
	"K00-801": "OXXMjeaqyCy",
	"N30-1101": "SZ7gSwbwOeB",
	"A90-132": "vfHrAlD4kyw",
	"K00-751": "K378k0phJw7",
	"Z40-2022": "et7QxiucRUs",
	"P50-1515": "mJNZLvRw5Ui",
	"S00-1779": "qGbnNLnl303",
	"O00-1202": "TkbsEQtMuxA",
	"Q20-1554": "cKJQ4DhVWYf",
	"S00-1781": "S3kwFZgTfa7",
	"R00-1638": "oZCetwZzmJx",
	"G90-540": "raeF4ZYNM8I",
	"L20-944": "AA8WXQR4wRp",
	"R20-1676": "YSDq8GENIWf",
	"A15-35": "VI438cVzB9A",
	"A30-73": "uGmpxZdumRA",
	"A30-79": "biMak2lLyKB",
	"R10-1658": "LDNjLqxJ9pd",
	"B35-190": "F7bGDfmgZYQ",
	"Q90-1601": "EFK4i05FCOQ",
	"M20-1038": "WvfaGBDzJDc",
	"K00-800": "hR0quQYreP2",
	"R25-1697": "lyKvUdh7Bqp",
	"N70-1132": "c9xzfT60BNi",
	"X60-1913": "LsmbnKhTmQZ",
	"P20-1477": "mr7JkaDV9JP",
	"S30-1800": "QT9dHaSLBdx",
	"A30-62": "enb286wPugi",
	"E10-360": "KSm1SHp6SUK",
	"A00-12": "vNuMX91LfCV",
	"K55-858": "kv7YGTAN9XS",
	"E10-363": "GAt9rzfohGN",
	"L00-918": "OsXh8aHvUx4",
	"L50-967": "sH91B75uaa8",
	"A20-60": "SMq2ltM6Pyf",
	"P10-1457": "J8M6wR7YlML",
	"L20-938": "Uifvl3SEByZ",
	"O30-1286": "FBItmnl9OgH",
	"G70-523": "u0dnhlv1Uwx",
	"O20-1237": "AikNOq44C7a",
	"F20-459": "oj7HPcyhoPU",
	"C15-265": "FNxwYy2YZHw",
	"O20-1255": "txgF0BhqQsA",
	"E65-428": "AMlh4swl1vd",
	"N80-1161": "lBuNPCVgJZw",
	"B20-160": "VyRlhquDDML",
	"A50-88": "T5PKRdZJnqn",
	"I05-616": "LQwNiVwHsxX",
	"P20-1482": "fHkTpqjgfS8",
	"O00-1187": "tD4ktdfz6Yz",
	"R50-1742": "WzWTO1cA81a",
	"L60-980": "RZNSjBqQdcN",
	"Z00-1956": "YiETRIjzSHg",
	"S70-1821": "clgYIPA6AA9",
	"N70-1133": "jms0WzwFS3V",
	"Z40-2042": "sWkTLTajMU0",
	"B00-144": "LQldQFPlPn0",
	"C81-305": "hLn1wiUwxeW",
	"O20-1243": "s3PyYcVWjqz",
	"B20-164": "p7kRPdLxjzZ",
	"R00-1615": "AD4FCcK12sB",
	"R40-1710": "TuF54MjyVEu",
	"R20-1683": "LnELn1azl9i",
	"B20-159": "Ndpi7ghJpmI",
	"E10-362": "JilKPQvuU3T",
	"J00-712": "VpisYyHAfol",
	"R50-1763": "bdHcxQaofOR",
	"N10-1084": "KkG9kL8N6EN",
	"R50-1748": "tDerS4Fv9qi",
	"F20-458": "MVsdFm2WDKO",
	"R20-1670": "kDoow6RCqrK",
	"C76-300": "wuj91IU6xhM",
	"F90-490": "H9gMFVzlOZm",
	"I30-654": "C5zeTyEVEve",
	"E70-437": "GcZsq0O0J6Y",
	"K40-853": "DoS9pqH07ZP",
	"N80-1151": "H5uVGroYOet",
	"R10-1663": "MUZZtfwe77q",
	"Q20-1553": "MjrIyIBpERT",
	"Z30-2005": "D1Xm4RR8vYL",
	"D50-321": "eqCnrLkbOK5",
	"B95-252": "ATyNPoIX17l",
	"A65-107": "PlUUOLcf5Hy",
	"Z30-1986": "DAl4jMmwL8T",
	"A15-48": "BhDrm0MArlX",
	"K00-819": "AShcoExk4cX",
	"R10-1650": "AOSrrtktU8t",
	"Z00-1936": "FS4VD9EzaOb",
	"Z40-2009": "coc78KyBaHh",
	"O30-1300": "a3sPg6W2X5F",
	"P90-1537": "c61kyZnfb1y",
	"G40-495": "b9LcfhtaTCY",
	"R50-1744": "lRl3oATJ0xa",
	"Z00-1940": "OANhwecJakA",
	"D10-316": "XYMJS8kq63Q",
	"A50-99": "qPX1hG6FUDS",
	"C50-277": "UxZG06cauT5",
	"S80-1827": "MmOAlCuOEXg",
	"P20-1475": "hAHI13obEmN",
	"L20-937": "IoJEFuVDHZU",
	"R25-1695": "hLP5bYujjyP",
	"K40-841": "MAlzu7OfANL",
	"L55-973": "DcqKYUChqJg",
	"K35-833": "N6BiJQ0Z01O",
	"J00-715": "wghe7XJNAaW",
	"A90-129": "Yra2QYgUkVA",
	"R40-1713": "RjLzKVKspkL",
	"I10-621": "xUCe7zhzw0O",
	"Q65-1591": "VCoVv1VD24R",
	"P35-1499": "NmXFtcGRb5S",
	"K55-874": "g5chXpY2vYW",
	"F20-457": "eQOoxXbTJmj",
	"P00-1417": "mTJTDDr6FBW",
	"K00-760": "l0BryH9DOKN",
	"I80-698": "ePWpZvLqvpS",
	"T00-1836": "rlcqbKJMB8z",
	"Z40-2023": "Mbgu0EzBvI7",
	"K70-890": "t2KeZT58Z3V",
	"A30-65": "J1BgAydUhyU",
	"Q65-1589": "hp0cTgK7U6y",
	"R40-1729": "AuHXSha8hoI",
	"O30-1305": "zF8m83W0plG",
	"N80-1185": "ceWyAojq2Ro",
	"N80-1138": "h8DezmmSFEZ",
	"K00-785": "e1BskQoLosy",
	"M20-1040": "uJPqAMaPlSt",
	"N60-1123": "waiKB3Urgnm",
	"B00-142": "WBOG0Wl5NOJ",
	"O60-1317": "pd6V6Ger2xu",
	"R40-1711": "Cpak9pzi0pq",
	"M70-1065": "jrxONWXgYMM",
	"Z40-2010": "xfd9YKR7XYP",
	"A70-111": "o3izGUHrAPI",
	"I30-658": "mUUWP8iW4ou",
	"N30-1099": "T8qQRy2HJ2D",
	"H65-606": "TorNTX3o5HB",
	"M05-1019": "r0hzmceGvRq",
	"E50-423": "G4vuMLHozLI",
	"K00-776": "J6yjTYcWehu",
	"L60-974": "TrHq3ha6xny",
	"I20-625": "ffrhtkRhQYr",
	"M05-1027": "pqsMPxeyIrG",
	"I26-640": "VS6jzQ1taNc",
	"A30-74": "Cc8ATJ59SxW",
	"A80-118": "rKh7pm1Zjyt",
	"K80-897": "qMvZMSDZYyu",
	"E10-397": "W3pCdmp706r",
	"R25-1696": "qUXnpDhytyH",
	"H40-583": "x9x5jsAo2M8",
	"O60-1372": "KvZy6CS1MNe",
	"O60-1329": "OJIvCXoaBJE",
	"P90-1533": "AZA2n3NLbHB",
	"G40-504": "bhu4m8IbQ5Z",
	"A00-23": "NcCFb650rzR",
	"R40-1714": "FyuaWRKBXe6",
	"E00-337": "qjrfQSxE2jw",
	"F10-447": "o2AIKVz0mFR",
	"Z40-2035": "J3DlJ42sOcP",
	"P20-1481": "TgGB1KDdt2a",
	"N10-1081": "hCeNY9oxas3",
	"C81-308": "PBpuOpnS1Ls",
	"O60-1360": "SmgLz4Ru7n5",
	"Q65-1595": "ddfxf6yMqdg",
	"K00-773": "GJZrvoNC9Jx"
}